{"Joe Biden": {"unigram": {"('America',)": 32, "('Americans',)": 24, "('American',)": 22, "('world',)": 21, "('people',)": 20, "('make',)": 20, "('know',)": 18, "('get',)": 18, "('new',)": 17, "('families',)": 17, "('year',)": 15, "('jobs',)": 15, "('let',)": 14, "('Let',)": 14, "('us',)": 13, "('one',)": 13, "('keep',)": 13, "('nation',)": 12, "('going',)": 12, "('every',)": 12, "('costs',)": 12, "('care',)": 12, "('Putin',)": 12, "('\u201c',)": 11, "('pass',)": 11}, "bigram": {"('United', 'States')": 9, "('make', 'sure')": 7, "('health', 'care')": 5, "('Ukrainian', 'people')": 5, "('Rescue', 'Plan')": 5, "('American', 'Rescue')": 5, "('us', 'tonight')": 4, "('lower', 'costs')": 4, "('last', 'year,')": 4, "('tax', 'rate')": 3, "('police', 'officers')": 3, "('move', 'forward')": 3, "('mental', 'health')": 3, "('important', 'pass')": 3, "('get', 'done')": 3, "('free', 'world')": 3, "('fight', 'inflation')": 3, "('electric', 'vehicles,')": 3, "('days', 'ago,')": 3, "('burn', 'pits')": 3, "('around', 'world')": 3, "('Supreme', 'Court')": 3, "('young', 'people')": 2, "('world', 'ever')": 2, "('veterans', 'get')": 2}, "trigram": {"('American', 'Rescue', 'Plan')": 5, "('support', 'American', 'jobs')": 2, "('see', 'unity', 'among')": 2, "('restore', 'trust', 'safety')": 2, "('plan', 'fight', 'inflation')": 2, "('move', 'forward', 'safely')": 2, "('minimum', 'tax', 'rate')": 2, "('important', 'pass', 'Bipartisan')": 2, "('get', 'back', 'work')": 2, "('electric', 'vehicles,', 'creating')": 2, "('build', 'electric', 'vehicles,')": 2, "('billion', 'build', 'electric')": 2, "('United', 'States', 'Supreme')": 2, "('United', 'States', 'America')": 2, "('Type', '1', 'diabetes,')": 2, "('States', 'Supreme', 'Court')": 2, "('American', 'businesses', 'consumers')": 2, "('\u201d', 'revitalization', 'American')": 1, "('\u201d', 'initiative', 'people')": 1, "('\u201d', 'incinerated', 'wastes')": 1, "('\u201d', 'ground', 'America')": 1, "('\u201d', 'eight', 'state-of-the-art')": 1, "('\u201d', 'call', 'building')": 1, "('\u201d', 'Ukrainian', 'Ambassador')": 1, "('\u201d', 'Tonight', 'say')": 1}}, "Donald Trump": {"unigram": {"('America',)": 21, "('American',)": 18, "('world',)": 15, "('nation',)": 15, "('never',)": 13, "('great',)": 12, "('people',)": 11, "('new',)": 11, "('country',)": 11, "('\u2014',)": 9, "('citizens',)": 9, "('history',)": 8, "('every',)": 8, "('ever',)": 8, "('must',)": 7, "('could',)": 7, "('also',)": 7, "('administration',)": 7, "('United',)": 7, "('.,',)": 7, "('years',)": 6, "('want',)": 6, "('greatest',)": 6, "('achieved',)": 6, "('Americans',)": 6}, "bigram": {"('United', 'States')": 4, "('American', 'people')": 4, "('must', 'never')": 3, "('built', 'greatest')": 3, "('also', 'want')": 3, "('\u201c', 'medical')": 2, "('years', 'ago,')": 2, "('whole', 'world')": 2, "('want', 'thank')": 2, "('stock', 'market')": 2, "('serve', 'citizens')": 2, "('rebuilt', 'American')": 2, "('past', 'four')": 2, "('open', 'debate')": 2, "('new', 'administration')": 2, "('never', 'seen')": 2, "('national', 'greatness')": 2, "('make', 'America')": 2, "('history', 'world')": 2, "('greatest', 'economy')": 2, "('four', 'years,')": 2, "('everyday', 'citizens')": 2, "('every', 'citizen')": 2, "('economy', 'history')": 2, "('country', '.,')": 2}, "trigram": {"('past', 'four', 'years,')": 2, "('make', 'America', 'great')": 2, "('greatest', 'economy', 'history')": 2, "('economy', 'history', 'world')": 2, "('built', 'greatest', 'economy')": 2, "('Four', 'years', 'ago,')": 2, "('\u201d', 'wanted', 'make')": 1, "('\u201d', 'make', 'life')": 1, "('\u201d', 'Another', 'administration')": 1, "('\u201c', 'medical', 'miracle.')": 1, "('\u201c', 'medical', 'miracle,')": 1, "('\u201c', 'Made', 'USA.')": 1, "('\u201c', 'America', 'First')": 1, "('\u2014', 'safe,', 'strong,')": 1, "('\u2014', 'made', 'USA')": 1, "('\u2014', 'important', 'word')": 1, "('\u2014', 'great', 'privilege')": 1, "('\u2014', 'almost', 'everyone')": 1, "('years:', 'Space', 'Force')": 1, "('years,', 'one', 'image')": 1, "('years,', 'face', 'every')": 1, "('years,', 'American', 'people')": 1, "('years', 'develop', 'vaccine')": 1, "('years', 'ago,', 'launched')": 1, "('years', 'ago,', 'came')": 1}}, "Herbert Hoover": {"unigram": {"('Government',)": 23, "('economic',)": 20, "('Federal',)": 19, "('Congress',)": 18, "('people',)": 17, "('must',)": 17, "('upon',)": 15, "('system',)": 15, "('recovery',)": 12, "('country',)": 12, "('action',)": 12, "('national',)": 11, "('world',)": 9, "('shall',)": 9, "('agencies',)": 9, "('would',)": 8, "('works',)": 8, "('public',)": 8, "('measures',)": 8, "('great',)": 8, "('aid',)": 8, "('&',)": 8, "('#39;',)": 8, "('reduction',)": 7, "('progress',)": 7}, "bigram": {"('&', '#39;')": 8, "('per', 'cent')": 5, "('Reconstruction', 'Finance')": 5, "('social', 'economic')": 4, "('session', 'Congress')": 4, "('public', 'works')": 4, "('last', 'session')": 4, "('Federal', 'Government')": 4, "('toward', 'recovery')": 3, "('shocks', 'economic')": 3, "('four', 'years')": 3, "('Government', 'must')": 3, "('Finance', 'Corporation')": 3, "('Federal', 'public')": 3, "('Federal', 'Reserve')": 3, "('Farm', 'Loan')": 3, "('Executive', 'orders')": 3, "('veterans', '&')": 2, "('upon', 'state')": 2, "('undoubtedly', 'multiplied')": 2, "('tax', 'burdens')": 2, "('past', 'four')": 2, "('multiplied', 'weakness')": 2, "('manufacturers', '&')": 2, "('major', 'difficulties')": 2}, "trigram": {"('last', 'session', 'Congress')": 3, "('Reconstruction', 'Finance', 'Corporation')": 3, "('Federal', 'public', 'works')": 3, "('veterans', '&', '#39;')": 2, "('undoubtedly', 'multiplied', 'weakness')": 2, "('per', 'cent', 'reduction')": 2, "('past', 'four', 'years')": 2, "('manufacturers', '&', '#39;')": 2, "('information', 'upon', 'state')": 2, "('executive', 'administrative', 'agencies')": 2, "('Reconstruction', 'Finance', 'Corporation,')": 2, "('Federal', 'Reserve', 'System')": 2, "('Farm', 'Loan', 'Banks,')": 2, "('70', '33', '32')": 2, "('1/2', 'per', 'cent')": 2, "('&', '#39;', 'excise')": 2, "('#39;', 'excise', 'taxes')": 2, "('years', 'find', 'origins')": 1, "('years', 'ending', 'June')": 1, "('years', 'aid', 'employment')": 1, "('year,', 'including', 'naval')": 1, "('year', 'high', 'devotion')": 1, "('year', 'ending', 'June')": 1, "('year', 'continued', 'economy')": 1, "('year', '11', 'per')": 1}}, "Calvin Coolidge": {"unigram": {"('Washington',)": 23, "('man',)": 22, "('great',)": 18, "('first',)": 15, "('public',)": 13, "('years',)": 12, "('would',)": 12, "('country',)": 12, "('people',)": 11, "('made',)": 11, "('.\"',)": 11, "('national',)": 10, "('many',)": 10, "('American',)": 10, "('much',)": 9, "('time',)": 8, "('life',)": 8, "('government',)": 8, "('business',)": 8, "('large',)": 7, "('estate',)": 7, "('Government',)": 7, "('practical',)": 6, "('one',)": 6, "('never',)": 6}, "bigram": {"('&', '#39;')": 4, "('small', 'degree')": 3, "('man', 'affairs,')": 3, "('first', 'President')": 3, "('Mount', 'Vernon')": 3, "('young', 'man')": 2, "('western', 'lands')": 2, "('waterway', 'plan')": 2, "('true', 'greatness')": 2, "('public', 'office')": 2, "('private', 'public')": 2, "('practical', 'business')": 2, "('power', 'world')": 2, "('parts', 'country')": 2, "('one', 'first')": 2, "('national', 'government')": 2, "('man', 'affairs')": 2, "('held', 'time')": 2, "('greatest', 'man')": 2, "('great', 'man')": 2, "('executive', 'ability')": 2, "('business', 'man')": 2, "('business', 'ability')": 2, "('age', '21,')": 2, "('affairs', 'life')": 2}, "trigram": {"('\"Washington', '&', '#39;')": 2, "('youth', 'maturity,', 'experience')": 1, "('youth', 'maintained', 'throughout')": 1, "('youth', 'Washington', 'showed')": 1, "('young', 'people', 'country')": 1, "('young', 'man', 'considered')": 1, "('young', 'man', 'Old')": 1, "('young', 'colonel,', 'got')": 1, "('yet', 'great', 'American')": 1, "('years', 'subsequent', '1763')": 1, "('years', 'source', 'true')": 1, "('years', 'siege', 'Boston')": 1, "('years', 'large', 'holder')": 1, "('years', 'effort', 'Washington')": 1, "('years', 'earned', 'living')": 1, "('years', 'constantly', 'absorbing')": 1, "('years', 'ago', 'Congress')": 1, "('years', 'Mount', 'Vernon')": 1, "('wrought,', 'shall', 'also')": 1, "('wrote:\"', 'led', 'reflect')": 1, "('wrong', 'represent', 'heroic')": 1, "('written,', 'temptation', 'wrong')": 1, "('written,', 'many', 'people')": 1, "('writing', 'opposed', 'incorporation')": 1, "('writes,', '\"Washington', '&')": 1}}, "Woodrow Wilson": {"unigram": {"('world',)": 16, "('peace',)": 12, "('nations',)": 10, "('every',)": 9, "('representatives',)": 8, "('may',)": 8, "('international',)": 8, "('wish',)": 7, "('whose',)": 7, "('whole',)": 7, "('purpose',)": 7, "('program',)": 7, "('principle',)": 7, "('peoples',)": 7, "('people',)": 7, "('Russian',)": 7, "('Central',)": 7, "('upon',)": 6, "('terms',)": 6, "('spirit',)": 6, "('settlement',)": 6, "('objects',)": 6, "('must',)": 6, "('made',)": 6, "('justice',)": 6}, "bigram": {"('Russian', 'representatives')": 5, "('peace', 'world')": 4, "('&', 'mdash;')": 4, "('territorial', 'integrity')": 3, "('spirit', 'intention')": 3, "('representatives', 'Central')": 3, "('independence', 'territorial')": 3, "('among', 'nations')": 3, "('Central', 'Empires')": 3, "('Balkan', 'states')": 3, "('spokesmen', 'Central')": 2, "('several', 'Balkan')": 2, "('secure', 'access')": 2, "('political', 'economic')": 2, "('peoples', 'world')": 2, "('people', 'United')": 2, "('opportunity', 'autonomous')": 2, "('one', 'another')": 2, "('objects', 'war')": 2, "('nations', 'world')": 2, "('international', 'guarantees')": 2, "('guarantees', 'political')": 2, "('free', 'secure')": 2, "('free', 'nations')": 2, "('fair', 'dealing')": 2}, "trigram": {"('independence', 'territorial', 'integrity')": 3, "('several', 'Balkan', 'states')": 2, "('political', 'economic', 'independence')": 2, "('people', 'United', 'States')": 2, "('opportunity', 'autonomous', 'development')": 2, "('free', 'secure', 'access')": 2, "('economic', 'independence', 'territorial')": 2, "('yield', 'either', 'principle')": 1, "('yet', 'soul', 'subservient')": 1, "('years,', 'righted,', 'order')": 1, "('wrong', 'done', 'France')": 1, "('wrong', 'assertions', 'right')": 1, "('would', 'wish', 'respond,')": 1, "('would', 'willing', 'conclude')": 1, "('would', 'seem,', 'grim')": 1, "('would', 'deem', 'satisfactory')": 1, "('world,', 'general', 'terms,')": 1, "('world,', '&', 'mdash;')": 1, "('world', 'secured', 'recurrence')": 1, "('world', 'obtaining', 'unhampered')": 1, "('world', 'objects', 'war')": 1, "('world', 'nearly', 'fifty')": 1, "('world', 'made', 'fit')": 1, "('world', 'live,', '&')": 1, "('world', 'force', 'selfish')": 1}}, "William Taft": {"unigram": {"('agreement',)": 13, "('trade',)": 12, "('products',)": 11, "('Canada',)": 11, "('food',)": 10, "('Dominion',)": 10, "('country',)": 9, "('us',)": 8, "('two',)": 8, "('natural',)": 8, "('would',)": 7, "('free',)": 7, "('commercial',)": 7, "('supply',)": 6, "('resources',)": 6, "('reciprocal',)": 6, "('increase',)": 6, "('duties',)": 6, "('development',)": 6, "('countries',)": 6, "('relations',)": 5, "('policy',)": 5, "('people',)": 5, "('one',)": 5, "('made',)": 5}, "bigram": {"('trade', 'agreement')": 7, "('reciprocal', 'trade')": 5, "('natural', 'resources')": 4, "('two', 'countries')": 3, "('food', 'products')": 3, "('United', 'States')": 3, "('two', 'peoples')": 2, "('trade', 'relations')": 2, "('trade', 'agreement,')": 2, "('timber', 'resources')": 2, "('three', 'thousand')": 2, "('take', 'steps')": 2, "('supply', 'natural')": 2, "('sources', 'food')": 2, "('representatives', 'Dominion')": 2, "('relations', 'two')": 2, "('relations', 'Dominion')": 2, "('raw', 'materials,')": 2, "('products', 'necessities')": 2, "('placed', 'free')": 2, "('obtain', 'free')": 2, "('necessities', 'life,')": 2, "('natural', 'products')": 2, "('made', 'free')": 2, "('increase', 'price')": 2}, "trigram": {"('reciprocal', 'trade', 'agreement')": 4, "('representatives', 'Dominion', 'Government,')": 2, "('relations', 'two', 'countries')": 2, "('products', 'necessities', 'life,')": 2, "('placed', 'free', 'list,')": 2, "('obtain', 'free', 'entry')": 2, "('food', 'products', 'necessities')": 2, "('year,', '1910,', '$655,000,000')": 1, "('yardstick', 'measure', 'benefits')": 1, "('would', 'truly', 'national')": 1, "('would', 'steady', 'local')": 1, "('would', 'postpone', 'effect')": 1, "('would', 'mutually', 'advantageous')": 1, "('would', 'make', 'reduction')": 1, "('would', 'certainly', 'help')": 1, "('would', 'benefit', 'sections')": 1, "('world,', 'recent', 'increase')": 1, "('world', 'increase', 'price')": 1, "('world', 'food', 'natural')": 1, "('wool', 'sheep,', 'textile')": 1, "('wood', 'manufacture', 'print')": 1, "('without', 'substantial', 'injury')": 1, "('without', 'obstructing', 'prohibitory')": 1, "('without', 'artificial', 'natural')": 1, "('within', 'scope', 'agreement')": 1}}, "Theodore Roosevelt": {"unigram": {"('law',)": 16, "('would',)": 12, "('right',)": 12, "('one',)": 10, "('business',)": 10, "('Congress',)": 10, "('labor',)": 9, "('action',)": 9, "('upon',)": 8, "('law,',)": 8, "('necessary',)": 7, "('may',)": 7, "('among',)": 7, "('&',)": 7, "('#39;',)": 7, "('time',)": 6, "('reasonable',)": 6, "('present',)": 6, "('organizations',)": 6, "('made',)": 6, "('farmers',)": 6, "('contract',)": 6, "('combination',)": 6, "('bill',)": 6, "('anti-trust',)": 6}, "bigram": {"('&', '#39;')": 7, "('farmers', '&')": 4, "('restraint', 'trade')": 3, "('order', 'issued')": 3, "('necessary', 'among')": 3, "('anti-trust', 'law,')": 3, "('action', 'taken')": 3, "('#39;', 'organizations,')": 3, "('wood', 'pulp,')": 2, "('transaction', 'modern')": 2, "('time', 'limit')": 2, "('time', 'come')": 2, "('temporary', 'restraining')": 2, "('statute', 'books')": 2, "('savings', 'banks')": 2, "('right', 'make')": 2, "('restraining', 'order')": 2, "('recognized', 'legal')": 2, "('provision', 'made')": 2, "('present', 'session')": 2, "('postal', 'savings')": 2, "('peculiarly', 'province')": 2, "('organizations', 'farmers')": 2, "('one', 'another')": 2, "('modern', 'industrial')": 2}, "trigram": {"('farmers', '&', '#39;')": 4, "('&', '#39;', 'organizations,')": 3, "('temporary', 'restraining', 'order')": 2, "('restraining', 'order', 'issued')": 2, "('postal', 'savings', 'banks')": 2, "('organizations', 'farmers', '&')": 2, "('modern', 'industrial', 'world')": 2, "('labor', 'organizations', 'farmers')": 2, "('contract', 'one', 'another')": 2, "('combine', 'contract', 'one')": 2, "('years', 'ago,', 'act')": 1, "('wrongs', 'done', 'labor,')": 1, "('would', 'suggest,', 'merely')": 1, "('would', 'put', 'upon')": 1, "('would', 'provide', 'publicity')": 1, "('would', 'permit', 'act')": 1, "('would', 'necessitate', 'action')": 1, "('would', 'liable', 'attack')": 1, "('would', 'illegal', 'common')": 1, "('would', 'give', 'greater')": 1, "('would', 'enact', 'contract,')": 1, "('would', 'become', 'subject')": 1, "('would', 'apply', 'equally')": 1, "('would', 'achieve', 'desired')": 1, "('worth', 'considering', 'whether')": 1}}, "William McKinley": {"unigram": {"('world',)": 8, "('trade',)": 8, "('must',)": 8, "('people',)": 7, "('&',)": 7, "('#39;',)": 7, "('commercial',)": 6, "('policy',)": 5, "('part',)": 5, "('every',)": 5, "('ever',)": 5, "('United',)": 5, "('American',)": 5, "('would',)": 4, "('whose',)": 4, "('us',)": 4, "('products',)": 4, "('new',)": 4, "('nations',)": 4, "('longer',)": 4, "('less',)": 4, "('interest',)": 4, "('industrial',)": 4, "('great',)": 4, "('go',)": 4}, "bigram": {"('&', '#39;')": 7, "('world', '&')": 5, "('United', 'States')": 4, "('South', 'America')": 3, "('Central', 'South')": 3, "('western', 'coasts')": 2, "('mutual', 'exchange')": 2, "('every', 'part')": 2, "('art,', 'science,')": 2, "('Mexico', 'Central')": 2, "('years', 'toil')": 1, "('years', 'ago')": 1, "('wrought', 'exposition?')": 1, "('would', 'touched')": 1, "('would', 'clinging')": 1, "('would', 'best')": 1, "('would', 'advanced')": 1, "('world', 'single')": 1, "('workingmen', 'throughout')": 1, "('work', 'thoroughly,')": 1, "('work', 'go')": 1, "('wonderful', 'medium')": 1, "('wonderful', 'industrial')": 1, "('without', 'vanity')": 1, "('without', 'harm')": 1}, "trigram": {"('world', '&', '#39;')": 5, "('Central', 'South', 'America')": 3, "('Mexico', 'Central', 'South')": 2, "('years', 'toil', 'struggle,')": 1, "('years', 'ago', 'impenetrable')": 1, "('wrought', 'exposition?', 'Gentlemen,')": 1, "('would', 'touched', 'heart')": 1, "('would', 'clinging', 'clumsy')": 1, "('would', 'best', 'us')": 1, "('would', 'advanced', 'eighteenth')": 1, "('world', 'single', 'message')": 1, "('workingmen', 'throughout', 'United')": 1, "('work', 'thoroughly,', 'presenting')": 1, "('wonderful', 'medium', 'telegraphy')": 1, "('wonderful', 'industrial', 'development')": 1, "('without', 'vanity', 'boastfulness,')": 1, "('without', 'harm', 'industries')": 1, "('within', 'less', 'hour')": 1, "('wisdom', 'part', 'manufacturers')": 1, "('wisdom', 'energy', 'nations')": 1, "('widely', 'separated', 'peoples')": 1, "('whose', 'presence', 'participation')": 1, "('whose', 'mind', 'ever')": 1, "('whose', 'good', 'repeatedly')": 1, "('whose', 'generous', 'hospitality')": 1}}, "Grover Cleveland": {"unigram": {"('treaty',)": 6, "('common',)": 3, "('war',)": 2, "('two',)": 2, "('thus',)": 2, "('right',)": 2, "('result',)": 2, "('national',)": 2, "('may',)": 2, "('long',)": 2, "('countries',)": 2, "('assume',)": 2, "('arbitration',)": 2, "('yet',)": 1, "('working',)": 1, "('well',)": 1, "('views',)": 1, "('upon',)": 1, "('unlimited,',)": 1, "('ultimate',)": 1, "('tried',)": 1, "('transmit',)": 1, "('transmission',)": 1, "('transcendent',)": 1, "('traditions,',)": 1}, "bigram": {"('two', 'countries')": 2, "('yet', 'apparent')": 1, "('working', 'plan')": 1, "('well', 'fortunate')": 1, "('war', 'parties')": 1, "('war', 'often')": 1, "('views', 'advocates')": 1, "('upon', 'general')": 1, "('unlimited,', 'irrevocable')": 1, "('ultimate', 'ensuing')": 1, "('tried', 'happiest')": 1, "('treaty', 'sure')": 1, "('treaty', 'result')": 1, "('treaty', 'formulated')": 1, "('treaty', 'fail')": 1, "('treaty', 'arbitration')": 1, "('treaty', 'affords,')": 1, "('transmit', 'herewith')": 1, "('transmission', 'expression')": 1, "('transcendent', 'good')": 1, "('traditions,', 'common')": 1, "('tongue', 'joined')": 1, "('together', 'ties')": 1, "('ties', 'common')": 1, "('thus', 'tried')": 1}, "trigram": {"('yet', 'apparent', 'treaty')": 1, "('working', 'plan', 'disputes')": 1, "('well', 'fortunate', 'attempts')": 1, "('war', 'parties', 'remote')": 1, "('war', 'often', 'assume')": 1, "('views', 'advocates', 'immediate,')": 1, "('upon', 'general', 'scheme')": 1, "('unlimited,', 'irrevocable', 'arbitration')": 1, "('ultimate', 'ensuing', 'benefits')": 1, "('two', 'countries', 'reach')": 1, "('two', 'countries', 'immediately')": 1, "('tried', 'happiest', 'auspices,')": 1, "('treaty', 'sure', 'felt')": 1, "('treaty', 'result', 'long')": 1, "('treaty', 'formulated', 'makes')": 1, "('treaty', 'fail', 'everywhere')": 1, "('treaty', 'arbitration', 'matters')": 1, "('treaty', 'affords,', 'hesitate')": 1, "('transmit', 'herewith', 'treaty')": 1, "('transmission', 'expression', 'earnest')": 1, "('transcendent', 'good', 'treaty')": 1, "('traditions,', 'common', 'institutions,')": 1, "('tongue', 'joined', 'together')": 1, "('together', 'ties', 'common')": 1, "('ties', 'common', 'traditions,')": 1}}, "Chester A. Arthur": {"unigram": {"('canal',)": 13, "('treaty',)": 11, "('States',)": 11, "('Pacific',)": 11, "('Atlantic',)": 9, "('water',)": 8, "('miles',)": 8, "('may',)": 8, "('would',)": 7, "('vessels',)": 7, "('Nicaragua',)": 7, "('two',)": 6, "('means',)": 6, "('United',)": 6, "('San',)": 6, "('within',)": 5, "('upon',)": 5, "('trade',)": 5, "('lake',)": 5, "('great',)": 5, "('world',)": 4, "('work',)": 4, "('territory',)": 4, "('route',)": 4, "('present',)": 4}, "bigram": {"('United', 'States')": 5, "('Atlantic', 'Pacific')": 4, "('world', '&')": 3, "('water', 'communication')": 3, "('coasting', 'trade')": 3, "('&', '#39;')": 3, "('two', 'Governments')": 2, "('trade', 'Atlantic')": 2, "('sailing', 'vessels')": 2, "('new', 'surveys')": 2, "('mouth', 'San')": 2, "('intermediate', 'levels,')": 2, "('communication', 'Atlantic')": 2, "('canal', 'would')": 2, "('abundant', 'depth')": 2, "('York', 'San')": 2, "('San', 'Francisco')": 2, "('San', 'Carlos')": 2, "('Pacific', 'States,')": 2, "('New', 'York')": 2, "('10,000', 'miles')": 2, "('yielding', 'interest')": 1, "('years', 'life')": 1, "('would', 'unquestionably')": 1, "('would', 'thus')": 1}, "trigram": {"('world', '&', '#39;')": 3, "('water', 'communication', 'Atlantic')": 2, "('trade', 'Atlantic', 'Pacific')": 2, "('mouth', 'San', 'Carlos')": 2, "('communication', 'Atlantic', 'Pacific')": 2, "('York', 'San', 'Francisco')": 2, "('New', 'York', 'San')": 2, "('yielding', 'interest', 'return')": 1, "('years', 'life', 'nation,')": 1, "('would', 'unquestionably', 'immediately')": 1, "('would', 'thus', '43')": 1, "('would', 'somewhat', 'increased')": 1, "('would', 'single', 'tide')": 1, "('would', 'practice', 'limit')": 1, "('would', 'great,', 'amounting')": 1, "('would', 'arise', 'immediately,')": 1, "('world', 'sort', 'trust')": 1, "('work,', 'indispensable', 'one,')": 1, "('work,', 'great', 'cost')": 1, "('work,', 'appreciating', 'benefit')": 1, "('work', 'without', 'delay')": 1, "('work', 'probably', 'operation')": 1, "('work', 'possible', 'contingencies')": 1, "('work', 'magnitude', 'way')": 1, "('without', 'delay', 'treaty')": 1}}, "James A. Garfield": {"unigram": {"('people',)": 15, "('upon',)": 13, "('Government',)": 13, "('great',)": 11, "('Constitution',)": 11, "('States',)": 10, "('power',)": 9, "('made',)": 9, "('law',)": 9, "('authority',)": 9, "('shall',)": 8, "('us',)": 6, "('may',)": 6, "('government',)": 6, "('freedom',)": 6, "('danger',)": 6, "('Union',)": 6, "('Congress',)": 6, "('supreme',)": 5, "('suffrage',)": 5, "('rights',)": 5, "('protection',)": 5, "('new',)": 5, "('nation',)": 5, "('equal',)": 5}, "bigram": {"('United', 'States')": 3, "('times', 'greater')": 2, "('supreme', 'authority')": 2, "('sovereign', 'power')": 2, "('since', 'adoption')": 2, "('race', 'slavery')": 2, "('power', 'every')": 2, "('onward', 'march')": 2, "('negro', 'race')": 2, "('local', 'government')": 2, "('hundred', 'years')": 2, "('good', 'government')": 2, "('given', 'new')": 2, "('forces', 'people')": 2, "('concerning', 'controversies')": 2, "('commercial', 'nations')": 2, "('attention', 'Government')": 2, "('across', 'isthmus')": 2, "('North', 'South')": 2, "('National', 'Government')": 2, "('&', '#39;')": 2, "('yield', 'fullness')": 1, "('yet', 'received')": 1, "('yet', 'fought')": 1, "('years', 'since')": 1}, "trigram": {"('negro', 'race', 'slavery')": 2, "('yield', 'fullness', 'blessings')": 1, "('years', 'since', 'adoption')": 1, "('years', 'national', 'life--century')": 1, "('years', 'hence', 'children')": 1, "('wronged', 'enfeebled', 'both.It')": 1, "('wrong,', 'shall', 'proper')": 1, "('written', 'constitution', 'United')": 1, "('world', 'believe', 'supreme')": 1, "('world', '&', '#39;')": 1, "('work', 'sections', 'races')": 1, "('witnesses', 'Union', 'emerged')": 1, "('without', 'secured', 'mariners')": 1, "('without', 'parallel', 'history.Fruitful')": 1, "('without', 'compelling', 'withdrawal')": 1, "('within', 'jurisdiction;', 'enforce')": 1, "('within', 'jurisdiction,', 'makes')": 1, "('within', 'jurisdiction', 'criminal')": 1, "('within', 'authority', 'limitations')": 1, "('withdrawal', 'national-banknotes,', 'thus')": 1, "('wisdom', 'patriotism', 'Congress')": 1, "('wisdom', 'founders', 'given')": 1, "('win', 'grander', 'victories')": 1, "('wider', 'negro', 'suffrage')": 1, "('widening', 'circle', 'intelligence,')": 1}}, "Rutherford B. Hayes": {"unigram": {"('bonds',)": 16, "('banking',)": 16, "('bill',)": 12, "('banks',)": 11, "('national',)": 10, "('system',)": 9, "('shall',)": 8, "('security',)": 8, "('United',)": 8, "('section',)": 7, "('interest',)": 7, "('business',)": 6, "('upon',)": 5, "('refunding',)": 5, "('public',)": 5, "('present',)": 5, "('per',)": 5, "('measure',)": 5, "('deposit',)": 5, "('circulation',)": 5, "('capital',)": 5, "('3',)": 5, "('rate',)": 4, "('purchase',)": 4, "('issued',)": 4}, "bigram": {"('national', 'banking')": 6, "('banking', 'system')": 6, "('per', 'cent')": 4, "('United', 'States')": 4, "('3', 'per')": 4, "('refunding', 'national')": 3, "('existing', 'banks')": 3, "('cent', 'bonds')": 3, "('bonds', 'issued')": 3, "('bonds', 'United')": 3, "('United', 'States,')": 3, "('security', 'circulation')": 2, "('security', 'bill')": 2, "('section', 'bill')": 2, "('rate', 'taxation')": 2, "('rate', 'interest')": 2, "('purchase', 'deposit')": 2, "('passage', 'present')": 2, "('new', 'banks')": 2, "('national', 'debt')": 2, "('measure', 'refunding')": 2, "('issued', 'United')": 2, "('interest', 'ceased')": 2, "('interest', '3')": 2, "('entitled', '\"act')": 2}, "trigram": {"('per', 'cent', 'bonds')": 3, "('national', 'banking', 'system')": 3, "('bonds', 'United', 'States')": 3, "('3', 'per', 'cent')": 3, "('refunding', 'national', 'debt')": 2, "('rate', 'interest', '3')": 2, "('national', 'banking', 'system,')": 2, "('measure', 'refunding', 'national')": 2, "('issued', 'United', 'States,')": 2, "('interest', '3', 'per')": 2, "('deposit', 'security', 'circulation')": 2, "('banking', 'association', 'depositing')": 2, "('association', 'depositing', 'shall')": 2, "('Revised', 'Statutes', 'United')": 2, "('would,', 'become', 'law,')": 1, "('would', 'unwise', 'authorize')": 1, "('would', 'inevitably', 'bring')": 1, "('would', 'defeat', 'object')": 1, "('work', 'great', 'harm,')": 1, "('within', 'thirty', 'days')": 1, "('withdrawn,', 'provided', 'law,')": 1, "('withdrawal', 'currency', 'circulation')": 1, "('winding', 'banks', 'consequence,')": 1, "('whole', 'system,', 'taking')": 1, "('week', 'term', 'office')": 1}}, "Ulysses S. Grant": {"unigram": {"('country',)": 7, "('questions',)": 5, "('two',)": 4, "('result',)": 4, "('question',)": 4, "('one',)": 4, "('history',)": 4, "('Constitution',)": 4, "('Congress',)": 4, "('votes',)": 3, "('right',)": 3, "('provide',)": 3, "('people',)": 3, "('nation',)": 3, "('meet',)": 3, "('means',)": 3, "('may',)": 3, "('law',)": 3, "('election',)": 3, "('doubt',)": 3, "('decision',)": 3, "('bill',)": 3, "('States',)": 3, "('Chief',)": 3, "('would',)": 2}, "bigram": {"('result', 'election')": 2, "('questions', 'arising')": 2, "('first', 'time')": 2, "('Houses', 'Congress')": 2, "('Chief', 'Magistrate')": 2, "('would', 'deplorable')": 1, "('would', 'best')": 1, "('witness', 'irregular')": 1, "('without', 'resistance')": 1, "('without', 'law,')": 1, "('wise', 'constitutional')": 1, "('whose', 'decisions')": 1, "('whole', 'history')": 1, "('whether', 'one')": 1, "('whatever', 'aspect')": 1, "('wants', 'assured')": 1, "('votes', 'declared')": 1, "('votes', 'cast')": 1, "('votes', 'President')": 1, "('voted,', 'tie')": 1, "('vote', 'impossible,')": 1, "('vital', 'result,')": 1, "('upright', 'course')": 1, "('upon', 'disposition')": 1, "('unless', 'Houses')": 1}, "trigram": {"('would', 'deplorable', 'witness')": 1, "('would', 'best', 'applicable')": 1, "('witness', 'irregular', 'controversy')": 1, "('without', 'resistance', 'supporters')": 1, "('without', 'law,', 'States')": 1, "('wise', 'constitutional', 'means')": 1, "('whose', 'decisions', 'stand')": 1, "('whole', 'history', 'shows')": 1, "('whether', 'one', 'candidates')": 1, "('whatever', 'aspect', 'may')": 1, "('wants', 'assured', 'result')": 1, "('votes', 'declared', 'standing,')": 1, "('votes', 'cast', 'late')": 1, "('votes', 'President', 'Vice-President,')": 1, "('voted,', 'tie', 'vote')": 1, "('vote', 'impossible,', 'must')": 1, "('vital', 'result,', 'conditions')": 1, "('upright', 'course', 'law')": 1, "('upon', 'disposition', 'disputes')": 1, "('unless', 'Houses', 'Congress')": 1, "('unemployed,', 'capital', 'idle,')": 1, "('understood', 'upon', 'disposition')": 1, "('uncertainty', 'double', 'claim')": 1, "('two', 'receive', 'continue')": 1, "('two', 'citizens', 'elected,')": 1}}, "James Buchanan": {"unigram": {"('troops',)": 7, "('upon',)": 6, "('city',)": 6, "('President',)": 5, "('resolution',)": 4, "('public',)": 4, "('committee,',)": 4, "('select',)": 3, "('precautionary',)": 3, "('peace',)": 3, "('ordered',)": 3, "('inauguration',)": 3, "('country',)": 3, "('time',)": 2, "('seize',)": 2, "('security',)": 2, "('secret',)": 2, "('ought',)": 2, "('organization',)": 2, "('order',)": 2, "('opinion',)": 2, "('number',)": 2, "('men',)": 2, "('large',)": 2, "('first',)": 2}, "bigram": {"('select', 'committee,')": 3, "('inauguration', 'President')": 3, "('upon', 'capital')": 2, "('troops', 'ordered')": 2, "('secret', 'organization')": 2, "('peace', 'order')": 2, "('order', 'city')": 2, "('number', 'troops')": 2, "('adopt', 'precautionary')": 2, "('yet', 'House')": 1, "('withdrawing', 'troops')": 1, "('whole', 'country')": 1, "('whether', 'information')": 1, "('waited', 'precautionary')": 1, "('vast', 'importance')": 1, "('us,', 'air')": 1, "('upon', 'table')": 1, "('upon', 'revolutionary')": 1, "('upon', 'responsibility,')": 1, "('upon', 'part')": 1, "('troops', 'first')": 1, "('troops', 'city,')": 1, "('troops', 'city')": 1, "('troops', 'assembled')": 1, "('transpiring', 'around')": 1}, "trigram": {"('peace', 'order', 'city')": 2, "('yet', 'House', 'laid')": 1, "('whole', 'country', 'could')": 1, "('whether', 'information', 'conspiracy')": 1, "('waited', 'precautionary', 'measure')": 1, "('vast', 'importance', 'whole')": 1, "('us,', 'air', 'filled')": 1, "('upon', 'table', 'large')": 1, "('upon', 'revolutionary', 'events')": 1, "('upon', 'responsibility,', 'attack')": 1, "('upon', 'part', 'portion')": 1, "('upon', 'capital', 'public')": 1, "('upon', 'capital', 'prevent')": 1, "('troops', 'ordered', 'city?')": 1, "('troops', 'ordered', 'act')": 1, "('troops', 'first', 'ordered')": 1, "('troops', 'city,', 'kept;')": 1, "('troops', 'city', 'ought')": 1, "('troops', 'assembled', 'city')": 1, "('transpiring', 'around', 'us,')": 1, "('total', 'amount', '653')": 1, "('time', 'troops', 'ordered')": 1, "('time', 'apprehended,', 'followed,')": 1, "('threats', '.\"', 'circumstances,')": 1, "('thoroughly', 'investigated', 'committee,')": 1}}, "Franklin Pierce": {"unigram": {"('Army',)": 6, "('would',)": 5, "('military',)": 5, "('troops',)": 4, "('public',)": 4, "('Congress',)": 4, "('thus',)": 3, "('force',)": 3, "('wholly',)": 2, "('waste',)": 2, "('vast',)": 2, "('support',)": 2, "('supplies',)": 2, "('subject',)": 2, "('service,',)": 2, "('requisite',)": 2, "('remote',)": 2, "('provision',)": 2, "('persons',)": 2, "('peace',)": 2, "('pay',)": 2, "('part',)": 2, "('must',)": 2, "('merely',)": 2, "('men',)": 2}, "bigram": {"('thus', 'deprived')": 2, "('persons', 'connected')": 2, "('military', 'force')": 2, "('yet', 'successful')": 1, "('year', 'already')": 1, "('wrong', 'upon')": 1, "('would', 'subject')": 1, "('would', 'injurious')": 1, "('would', 'disastrous')": 1, "('would', 'direct')": 1, "('would', 'broken')": 1, "('without', 'means')": 1, "('withdrawal', 'troops')": 1, "('wholly', 'restrain')": 1, "('wholly', 'dependent')": 1, "('white', 'inhabitants;')": 1, "('welfare', 'Union')": 1, "('waste', 'millions')": 1, "('waste', 'consequent')": 1, "('war', 'extermination')": 1, "('waging', 'war')": 1, "('vital', 'interest')": 1, "('violation', 'public')": 1, "('vicious', 'propensities')": 1, "('vested', 'law')": 1}, "trigram": {"('yet', 'successful', 'result')": 1, "('year', 'already', 'caused')": 1, "('wrong', 'upon', 'persons')": 1, "('would', 'subject', 'suffering')": 1, "('would', 'injurious', 'inhabitants')": 1, "('would', 'disastrous', 'demand')": 1, "('would', 'direct', 'immediate')": 1, "('would', 'broken', 'Army')": 1, "('without', 'means', 'regaining')": 1, "('withdrawal', 'troops', 'therefrom,')": 1, "('wholly', 'restrain', 'vicious')": 1, "('wholly', 'dependent', 'appropriations')": 1, "('white', 'inhabitants;', 'although')": 1, "('waste', 'millions', 'public')": 1, "('waste', 'consequent', 'forced')": 1, "('war', 'extermination', 'white')": 1, "('waging', 'war', 'extermination')": 1, "('vital', 'interest', 'peace')": 1, "('violation', 'public', 'honor')": 1, "('vested', 'law', 'Secretary')": 1, "('vast', 'tract', 'country')": 1, "('vast', 'regions', 'occupies')": 1, "('upon', 'persons', 'connected')": 1, "('unaccomplished,', 'would', 'injurious')": 1, "('two', 'Houses', 'order')": 1}}, "Millard Fillmore": {"unigram": {"('country',)": 29, "('United',)": 28, "('States',)": 25, "('Government',)": 24, "('upon',)": 22, "('made',)": 22, "('subject',)": 21, "('last',)": 21, "('public',)": 20, "('may',)": 20, "('foreign',)": 20, "('Department',)": 16, "('Congress',)": 15, "('part',)": 14, "('would',)": 13, "('two',)": 13, "('attention',)": 13, "('year',)": 12, "('without',)": 12, "('regard',)": 12, "('present',)": 12, "('nations',)": 12, "('must',)": 12, "('law',)": 12, "('duty',)": 12}, "bigram": {"('United', 'States')": 19, "('&', '#39;')": 10, "('last', 'session')": 6, "('United', 'States,')": 6, "('last', 'fiscal')": 4, "('fiscal', 'year')": 4, "('charge', '&')": 4, "('Secretary', 'State')": 4, "('Rio', 'Grande')": 4, "('Great', 'Britain')": 4, "('#39;', 'affaires')": 4, "('#39;', '&')": 4, "('within', 'limits')": 3, "('two', 'Governments')": 3, "('survey', 'Rio')": 3, "('set', 'apart')": 3, "('report', 'Secretary')": 3, "('foreign', 'powers')": 3, "('call', 'attention')": 3, "('Secretary', 'Interior')": 3, "('New', 'Mexico')": 3, "('would', 'also')": 2, "('whole', 'country')": 2, "('weight', 'measure')": 2, "('used', 'expended')": 2}, "trigram": {"('charge', '&', '#39;')": 4, "('&', '#39;', 'affaires')": 4, "('&', '#39;', '&')": 4, "('#39;', '&', '#39;')": 4, "('survey', 'Rio', 'Grande')": 3, "('last', 'fiscal', 'year')": 3, "('treaty', 'stipulations', 'Mexico')": 2, "('southern', 'boundary', 'New')": 2, "('ship', 'canal', 'two')": 2, "('report', 'Secretary', 'Interior')": 2, "('provision', 'made', 'law')": 2, "('port', 'San', 'Juan')": 2, "('ministers', 'France', 'England')": 2, "('made', 'last', 'session')": 2, "('line', 'New', 'Mexico')": 2, "('late', 'Secretary', 'State')": 2, "('last', 'session', 'Congress')": 2, "('lands', 'within', 'limits')": 2, "('intercourse', 'United', 'States')": 2, "('exclusive', 'trust', 'funds,')": 2, "('duty', 'call', 'attention')": 2, "('deem', 'duty', 'call')": 2, "('commercial', 'intercourse', 'United')": 2, "('close', 'last', 'session')": 2, "('citizens', 'United', 'States')": 2}}, "Zachary Taylor": {"unigram": {"('treaty',)": 11, "('may',)": 7, "('protection',)": 6, "('nations',)": 6, "('United',)": 6, "('Senate',)": 6, "('great',)": 5, "('canal',)": 5, "('territory',)": 4, "('passage',)": 4, "('States',)": 4, "('New',)": 4, "('Great',)": 4, "('Granada',)": 4, "('Central',)": 4, "('well',)": 3, "('time',)": 3, "('part',)": 3, "('object',)": 3, "('might',)": 3, "('contemplated',)": 3, "('construction',)": 3, "('across',)": 3, "('accordance',)": 3, "('Pacific',)": 3}, "bigram": {"('United', 'States')": 4, "('New', 'Granada')": 4, "('Great', 'Britain')": 3, "('treaty', 'New')": 2, "('ship', 'canal')": 2, "('regard', 'ratification,')": 2, "('protection', 'contemplated')": 2, "('great', 'maritime')": 2, "('canal', 'territory')": 2, "('advice', 'regard')": 2, "('Granada', 'protection')": 2, "('February,', '1847,')": 2, "('Central', 'America')": 2, "('Atlantic', 'Pacific')": 2, "('10th', 'February,')": 2, "('yields', 'protection')": 1, "('would', 'embrace')": 1, "('would', 'desire')": 1, "('world', 'stake')": 1, "('work', '.\"')": 1, "('wish', 'understood')": 1, "('wisdom', 'see')": 1, "('whole', 'spirit')": 1, "('well', 'expressed')": 1, "('well', 'every')": 1}, "trigram": {"('treaty', 'New', 'Granada')": 2, "('advice', 'regard', 'ratification,')": 2, "('New', 'Granada', 'protection')": 2, "('10th', 'February,', '1847,')": 2, "('yields', 'protection', 'capitalists')": 1, "('would', 'embrace', 'offer')": 1, "('would', 'desire', 'seize')": 1, "('world', 'stake', 'important')": 1, "('work', '.\"', 'also')": 1, "('wish', 'understood', 'reference')": 1, "('wisdom', 'see', 'fit')": 1, "('whole', 'spirit', 'resolution')": 1, "('well', 'expressed', 'immediate')": 1, "('well', 'every', 'interoceanic')": 1, "('well', 'calculated', 'diffuse')": 1, "('weak', 'sister', 'republics')": 1, "('wars', 'revolutions', 'may')": 1, "('views', 'expressed', 'message')": 1, "('views', 'entertained,', 'far')": 1, "('use', 'nations', 'equal')": 1, "('upon', 'wars', 'revolutions')": 1, "('upon', 'Government', 'either')": 1, "('undertaking', 'complete', 'work')": 1, "('undertake', 'open', 'communication')": 1, "('undertake', 'construct', 'canal')": 1}}, "James K. Polk": {"unigram": {"('treaty',)": 49, "('United',)": 42, "('Mexican',)": 41, "('article',)": 26, "('Senate',)": 26, "('States',)": 25, "('Government',)": 23, "('treaty,',)": 21, "('Mexico',)": 17, "('amended',)": 15, "('commissioners',)": 14, "('Congress',)": 14, "('ratified',)": 13, "('States,',)": 13, "('President',)": 13, "('would',)": 10, "('protocol',)": 10, "('territories',)": 9, "('may',)": 9, "('free',)": 9, "('communicated',)": 9, "('1848,',)": 9, "('shall',)": 8, "('said',)": 8, "('inhabitants',)": 8}, "bigram": {"('United', 'States')": 25, "('United', 'States,')": 13, "('Senate', 'United')": 11, "('Mexican', 'Government')": 10, "('amended', 'Senate')": 8, "('treaty', 'amended')": 7, "('article', 'treaty')": 7, "('commissioners', 'United')": 6, "('ceded', 'territories')": 6, "('ninth', 'article')": 5, "('minister', 'foreign')": 5, "('Mexican', 'Congress')": 5, "('tenth', 'article')": 4, "('legitimate', 'titles')": 4, "('free', 'exercise')": 4, "('exercise', 'religion')": 4, "('exchange', 'ratifications')": 4, "('article', 'treaty,')": 4, "('Secretary', 'State')": 4, "('Mexican', 'minister')": 4, "('Mexican', 'Republic')": 4, "('Mexican', 'Government,')": 4, "('House', 'Representatives')": 4, "('6th', 'July')": 4, "('*', '*')": 4}, "trigram": {"('treaty', 'amended', 'Senate')": 6, "('Senate', 'United', 'States,')": 6, "('commissioners', 'United', 'States')": 5, "('amended', 'Senate', 'United')": 5, "('Senate', 'United', 'States')": 5, "('free', 'exercise', 'religion')": 4, "('Mexican', 'minister', 'foreign')": 4, "('minister', 'foreign', 'affairs')": 3, "('message', '6th', 'July')": 3, "('inhabitants', 'ceded', 'territories')": 3, "('exercise', 'religion', 'without')": 3, "('Government', 'United', 'States')": 3, "('6th', 'July', 'last,')": 3, "('treaty,', 'amended', 'Senate')": 2, "('treaty', 'form', 'ratified')": 2, "('treaty', 'Mexican', 'Congress,')": 2, "('third', 'article', 'treaty')": 2, "('tenth', 'article', 'treaty')": 2, "('secured', 'free', 'exercise')": 2, "('rights', 'citizens', 'United')": 2, "('religion', 'without', 'restriction')": 2, "('ratification', 'Mexican', 'Government')": 2, "('protected', 'free', 'enjoyment')": 2, "('property', 'secured', 'free')": 2, "('ninth', 'article', 'treaty,')": 2}}, "John Tyler": {"unigram": {"('policy',)": 7, "('crew',)": 6, "('slave',)": 5, "('American',)": 5, "('vessel',)": 4, "('trade,',)": 4, "('adopted',)": 4, "('British',)": 4, "('upon',)": 3, "('traffic',)": 3, "('trade',)": 3, "('suppress',)": 3, "('subject',)": 3, "('slaves,',)": 3, "('slaves',)": 3, "('put',)": 3, "('new',)": 3, "('means',)": 3, "('made',)": 3, "('deeply',)": 3, "('citizens',)": 3, "('cargo',)": 3, "('captured',)": 3, "('board',)": 3, "('back',)": 3}, "bigram": {"('policy', 'adopted')": 3, "('crew', 'put')": 3, "('upon', 'subject')": 2, "('put', 'board')": 2, "('passenger', 'crew')": 2, "('new', 'crew')": 2, "('large', 'interests')": 2, "('citizens', 'deeply')": 2, "('board', 'passengers')": 2, "('West', 'Indies')": 2, "('United', 'States')": 2, "('Britannic', 'Majesty')": 2, "('American', 'crew')": 2, "('zealous', 'efforts')": 1, "('yet,', 'little')": 1, "('yet', 'principally,')": 1, "('years;', 'officers')": 1, "('would', 'seem')": 1, "('would', 'effect')": 1, "('worthy', 'consideration')": 1, "('workshops;', 'slaves,')": 1, "('whole', 'progress')": 1, "('whole', 'number')": 1, "('whether', 'torn')": 1, "('whether', 'measures')": 1}, "trigram": {"('passenger', 'crew', 'put')": 2, "('crew', 'put', 'board')": 2, "('zealous', 'efforts', 'matter')": 1, "('yet,', 'little', 'success,')": 1, "('yet', 'principally,', 'ignorant')": 1, "('years;', 'officers', 'crews')": 1, "('would', 'seem', 'regular')": 1, "('would', 'effect', 'continuance')": 1, "('worthy', 'consideration', 'whether')": 1, "('workshops;', 'slaves,', 'captured,')": 1, "('whole', 'progress', 'tortuous')": 1, "('whole', 'number', 'slaves')": 1, "('whether', 'torn', 'country')": 1, "('whether', 'measures', 'existing')": 1, "('wherever', 'perpetrated,', 'many')": 1, "('well', 'citizens', 'deeply')": 1, "('warrant', 'belief', 'citizens')": 1, "('voyage,', 'yet', 'principally,')": 1, "('voyage,', 'employees', 'Brazil')": 1, "('vessels,', 'knowledge,', 'good')": 1, "('vessels', 'receive', 'whole')": 1, "('vessel,', 'either', 'directly')": 1, "('vessel', 'nominally', 'chartered')": 1, "('vessel', 'delivered,', 'name')": 1, "('vessel', 'clears', 'United')": 1}}, "William Harrison": {"unigram": {"('power',)": 43, "('upon',)": 32, "('may',)": 32, "('Constitution',)": 32, "('people',)": 29, "('one',)": 26, "('&',)": 24, "('would',)": 21, "('great',)": 21, "('spirit',)": 19, "('country',)": 19, "('States',)": 19, "('mdash;',)": 17, "('Government',)": 17, "('character',)": 16, "('Executive',)": 15, "('rights',)": 14, "('part',)": 14, "('citizens',)": 14, "('well',)": 13, "('powers',)": 13, "('every',)": 13, "('public',)": 11, "('liberty',)": 11, "('free',)": 11}, "bigram": {"('&', 'mdash;')": 17, "('United', 'States')": 7, "('&', '#39;')": 7, "('grant', 'power')": 4, "('upon', 'acts')": 3, "('state', 'things')": 3, "('spirit', 'liberty')": 3, "('power', 'granted')": 3, "('placed', 'hands')": 3, "('framers', 'Constitution')": 3, "('executive', 'department')": 3, "('called', 'upon')": 3, "('Mr.', 'Jefferson')": 3, "('Executive', 'power')": 3, "('Chief', 'Magistrate')": 3, "('American', 'citizen')": 3, "('would', 'become')": 2, "('whole', 'country')": 2, "('want', 'conformity')": 2, "('upon', 'perform')": 2, "('upon', 'part')": 2, "('tie', 'interest,')": 2, "('second', 'term')": 2, "('respectively', 'claim')": 2, "('reserved', 'rights')": 2}, "trigram": {"('powers', 'respectively', 'claim')": 2, "('one', '&', '#39;')": 2, "('negative', 'upon', 'acts')": 2, "('means', 'placed', 'hands')": 2, "('may', 'observed,', 'however,')": 2, "('freedom', 'elective', 'franchise')": 2, "('exclusive', 'metallic', 'currency')": 2, "('country', '&', '#39;')": 2, "('controlling', 'freedom', 'elective')": 2, "('called', 'upon', 'perform')": 2, "('Constitution', 'United', 'States')": 2, "('zealously', 'contended', 'preservation')": 1, "('yet,', 'continuance', 'name')": 1, "('yet', 'judiciary', 'forms')": 1, "('yet', 'begun', 'soon')": 1, "('yet', 'ages', 'neither')": 1, "('years', 'since', 'remark')": 1, "('years', 'past', 'direction,,')": 1, "('years', '&', '#39;')": 1, "('year', 'among,', 'living,')": 1, "('written,', 'disputes', 'arisen')": 1, "('writings', 'made', 'us')": 1, "('writing', 'speaking,', 'unrestrained')": 1, "('writers', 'upon', 'species')": 1, "('writer', '\"Roman', 'senate')": 1}}, "Martin Van Buren": {"unigram": {"('State',)": 16, "('Government',)": 13, "('upon',)": 12, "('Maine',)": 11, "('governor',)": 10, "('territory',)": 8, "('Great',)": 8, "('would',)": 7, "('two',)": 7, "('jurisdiction',)": 7, "('Maine,',)": 7, "('may',)": 6, "('New',)": 6, "('British',)": 6, "('question',)": 5, "('party',)": 5, "('land',)": 5, "('exclusive',)": 5, "('also',)": 5, "('agent',)": 5, "('United',)": 5, "('Federal',)": 5, "('Britain',)": 5, "('view',)": 4, "('timber',)": 4}, "bigram": {"('land', 'agent')": 5, "('State', 'Maine')": 5, "('Great', 'Britain')": 5, "('governor', 'Maine')": 4, "('Federal', 'Government')": 4, "('two', 'Governments')": 3, "('United', 'States')": 3, "('Secretary', 'State')": 3, "('Province', 'New')": 3, "('New', 'Brunswick,')": 3, "('New', 'Brunswick')": 3, "('Great', 'Britain,')": 3, "('General', 'Government')": 3, "('upon', 'assumption')": 2, "('two', 'nations')": 2, "('territory', 'dispute')": 2, "('settlement', 'boundary')": 2, "('resort', 'force')": 2, "('portion', 'territory')": 2, "('mutual', 'exercise')": 2, "('military', 'occupation')": 2, "('lieutenant-governor', 'New')": 2, "('governor', 'Maine,')": 2, "('exercise', 'jurisdiction')": 2, "('exclusive', 'jurisdiction')": 2}, "trigram": {"('mutual', 'exercise', 'jurisdiction')": 2, "('land', 'agent', 'party')": 2, "('answer', 'Secretary', 'State')": 2, "('United', 'States', 'Great')": 2, "('States', 'Great', 'Britain')": 2, "('Province', 'New', 'Brunswick,')": 2, "('would', 'upon', 'condition')": 1, "('would', 'set', 'naught')": 1, "('would', 'regarded', 'transaction')": 1, "('would', 'postpone,', 'defeat,')": 1, "('would', 'materially', 'change')": 1, "('would', 'feel', 'duty')": 1, "('would', 'enable', 'arrest')": 1, "('without', 'authority', 'sanction')": 1, "('without', 'aid', 'strong')": 1, "('within', 'jurisdiction', 'Maine,')": 1, "('within', 'exercised', 'party')": 1, "('wishes', 'people', 'sister')": 1, "('whole', 'matter', 'invite')": 1, "('whither', 'repaired', 'purpose')": 1, "('whatever', 'considered,', 'manner')": 1, "('well', 'respect', 'position')": 1, "('welfare', 'unconscious),', 'solicitude')": 1, "('watered', 'river', 'Aroostook')": 1, "('warranted', 'general', 'forbearance')": 1}}, "Andrew Jackson": {"unigram": {"('Texas',)": 10, "('States',)": 10, "('United',)": 9, "('independence',)": 8, "('us',)": 7, "('country',)": 7, "('Congress',)": 6, "('upon',)": 5, "('shall',)": 5, "('power',)": 5, "('one',)": 5, "('new',)": 5, "('Mexico',)": 5, "('subject',)": 4, "('policy',)": 4, "('people',)": 4, "('last',)": 4, "('government',)": 4, "('given',)": 4, "('foreign',)": 4, "('course',)": 4, "('character',)": 4, "('acknowledgment',)": 4, "('Government',)": 4, "('Executive',)": 4}, "bigram": {"('United', 'States')": 6, "('independence', 'Texas')": 3, "('people', 'country')": 2, "('last', 'session')": 2, "('information', 'given')": 2, "('given', 'Congress')": 2, "('foreign', 'powers')": 2, "('contending', 'parties')": 2, "('acknowledgment', 'independence')": 2, "('United', 'States,')": 2, "('States', 'avoid')": 2, "('House', 'Representatives')": 2, "('would', 'left')": 1, "('would', 'difficult')": 1, "('would', 'certainly')": 1, "('world', 'uniform')": 1, "('wonted', 'caution')": 1, "('without', 'remark')": 1, "('without', 'reference')": 1, "('within', 'confines')": 1, "('wisely', 'consistent')": 1, "('wise', 'deliberation,')": 1, "('whole', 'subject')": 1, "('whether', 'Old')": 1, "('whenever', 'satisfactory')": 1}, "trigram": {"('information', 'given', 'Congress')": 2, "('United', 'States', 'avoid')": 2, "('would', 'left', 'without')": 1, "('would', 'difficult', 'United')": 1, "('would', 'certainly', 'afford')": 1, "('world', 'uniform', 'policy')": 1, "('without', 'remark', 'information')": 1, "('without', 'reference', 'particular')": 1, "('within', 'confines', '.,')": 1, "('wisely', 'consistent', 'principles')": 1, "('wise', 'deliberation,', 'assurance')": 1, "('whole', 'subject', 'would')": 1, "('whether', 'Old', 'New')": 1, "('whenever', 'satisfactory', 'information')": 1, "('well', 'understood', 'favor')": 1, "('war;', 'power', 'nowhere')": 1, "('war,', 'previous', 'understanding')": 1, "('war,', 'always', 'liable')": 1, "('war', 'alone', 'declared,')": 1, "('waited,', 'ability', 'new')": 1, "('views', 'much', 'reflection')": 1, "('views', 'merits', 'original')": 1, "('views', 'Congress', 'make')": 1, "('view,', 'ground', 'expediency,')": 1, "('view', 'subsequent', 'acquisition')": 1}}, "John Quincy Adams": {"unigram": {"('upon',)": 9, "('United',)": 9, "('may',)": 8, "('States',)": 8, "('principles',)": 7, "('nations',)": 6, "('American',)": 5, "('subject',)": 4, "('southern',)": 4, "('future',)": 4, "('far',)": 4, "('yet',)": 3, "('without',)": 3, "('take',)": 3, "('neither',)": 3, "('intercourse',)": 3, "('independence,',)": 3, "('Senate',)": 3, "('Republics',)": 3, "('Governments',)": 3, "('European',)": 3, "('Congress',)": 3, "('within',)": 2, "('welfare',)": 2, "('war',)": 2}, "bigram": {"('United', 'States')": 8, "('States', 'may')": 3, "('southern', 'nations')": 2, "('southern', 'Republics')": 2, "('influence', 'United')": 2, "('form', 'subject')": 2, "('American', 'nations')": 2, "('yielded', 'friendly')": 1, "('yet', 'far')": 1, "('yet', 'convinced')": 1, "('yet', 'another')": 1, "('years', 'since')": 1, "('would', 'improper')": 1, "('world', 'principle')": 1, "('without', 'toleration')": 1, "('without', 'entering')": 1, "('without', 'carried')": 1, "('within', 'constitutional')": 1, "('within', 'borders')": 1, "('wisdom', 'solitary')": 1, "('welfare', 'disposition')": 1, "('war,', 'also')": 1, "('war', 'speedier')": 1, "('war', 'southern')": 1, "('us', 'yielded')": 1}, "trigram": {"('United', 'States', 'may')": 3, "('influence', 'United', 'States')": 2, "('yielded', 'friendly', 'expostulation')": 1, "('yet', 'far', 'dominion')": 1, "('yet', 'convinced', 'justice')": 1, "('yet', 'another', 'subject')": 1, "('years', 'since', 'announced')": 1, "('would', 'improper', 'dwell')": 1, "('world', 'principle', 'resulting')": 1, "('without', 'toleration', 'dominant')": 1, "('without', 'entering', 'treaty,')": 1, "('without', 'carried', 'effect')": 1, "('within', 'constitutional', 'competency')": 1, "('within', 'borders', 'may')": 1, "('wisdom', 'solitary', 'efforts')": 1, "('welfare', 'disposition', 'comply')": 1, "('war,', 'also', 'form')": 1, "('war', 'speedier', 'termination,')": 1, "('war', 'southern', 'Republics')": 1, "('us', 'yielded', 'friendly')": 1, "('urged', 'disinterested', 'friendly')": 1, "('upon,', 'without', 'entering')": 1, "('upon', 'yet', 'convinced')": 1, "('upon', 'projects', 'purposes')": 1, "('upon', 'objects', 'peculiar')": 1}}, "James Monroe": {"unigram": {"('every',)": 32, "('great',)": 29, "('may',)": 27, "('made',)": 22, "('would',)": 21, "('public',)": 21, "('last',)": 20, "('United',)": 20, "('government',)": 18, "('might',)": 17, "('state',)": 15, "('relations',)": 15, "('object',)": 15, "('states',)": 14, "('present',)": 14, "('governments',)": 14, "('commerce',)": 14, "('States',)": 14, "('parties',)": 13, "('effect',)": 13, "('war',)": 12, "('since',)": 12, "('act',)": 12, "('within',)": 11, "('tribes',)": 11}, "bigram": {"('United', 'States')": 14, "('last', 'session')": 6, "('within', 'limits')": 5, "('public', 'debt')": 5, "('every', 'part')": 5, "('vast', 'territory')": 4, "('United', 'States,')": 4, "('&', 'mdash;')": 4, "('tribes', 'residing')": 3, "('report', 'Secretary')": 3, "('relations', 'every')": 3, "('reason', 'believe')": 3, "('progress', 'made')": 3, "('new', 'states')": 3, "('late', 'war')": 3, "('information', 'respecting')": 3, "('hope', 'may')": 3, "('great', 'purposes')": 3, "('friendly', 'relations')": 3, "('amount', 'public')": 3, "('Supreme', 'Court')": 3, "('Congress', 'last')": 3, "('whole', 'amount')": 2, "('view', 'presented')": 2, "('various', 'duties')": 2}, "trigram": {"('whole', 'amount', 'public')": 2, "('tribes', 'within', 'limits')": 2, "('throughout', 'every', 'portion')": 2, "('suppression', 'slave', 'trade')": 2, "('route', 'Potomac', 'Ohio')": 2, "('loan', '$5', 'million')": 2, "('friendly', 'relations', 'every')": 2, "('estimated', 'receipts', 'Treasury')": 2, "('amount', 'public', 'debt')": 2, "('act', '26th', 'May')": 2, "('Congress', 'last', 'session')": 2, "('youth,', 'continued', 'since')": 1, "('youngest', 'among', 'us')": 1, "('yielded', 'accommodation', 'power')": 1, "('yet', 'treaty', 'formed')": 1, "('yet', 'thoroughly', 'removed.It')": 1, "('yet', 'known.For', 'full')": 1, "('yet', 'finally', 'concluded')": 1, "('yet', 'entirely', 'removed')": 1, "('yet', 'arranged,', 'treaty')": 1, "('yet', 'accomplished.It', 'hoped')": 1, "('years,', 'without', 'seriously')": 1, "('years,', 'government', 'left')": 1, "('years', 'since', 'proclaimed')": 1, "('years', 'first', 'October')": 1}}, "James Madison": {"unigram": {"('power',)": 13, "('powers',)": 8, "('general',)": 7, "('States',)": 7, "('would',)": 6, "('Constitution',)": 6, "('laws',)": 5, "('United',)": 5, "('Congress',)": 5, "('water',)": 4, "('roads',)": 4, "('navigation',)": 4, "('legislative',)": 4, "('bill',)": 4, "('State',)": 4, "('within',)": 3, "('welfare\"',)": 3, "('several',)": 3, "('provided',)": 3, "('necessary',)": 3, "('effect',)": 3, "('defense',)": 3, "('courses,',)": 3, "('common',)": 3, "('commerce',)": 3}, "bigram": {"('navigation', 'water')": 4, "('United', 'States')": 4, "('would', 'effect')": 3, "('water', 'courses,')": 3, "('roads', 'canals,')": 3, "('general', 'welfare\"')": 3, "('defense', 'general')": 3, "('powers', 'vested')": 2, "('powers', 'General')": 2, "('power', 'construct')": 2, "('power', 'Congress')": 2, "('order', 'facilitate,')": 2, "('legislative', 'powers')": 2, "('latitude', 'construction')": 2, "('improve', 'navigation')": 2, "('general', 'power')": 2, "('facilitate,', 'promote,')": 2, "('construct', 'roads')": 2, "('common', 'defense')": 2, "('commerce', 'among')": 2, "('canals,', 'improve')": 2, "('among', 'several')": 2, "('State', 'Governments,')": 2, "('General', 'State')": 2, "('Congress', 'specified')": 2}, "trigram": {"('navigation', 'water', 'courses,')": 3, "('defense', 'general', 'welfare\"')": 3, "('roads', 'canals,', 'improve')": 2, "('powers', 'General', 'State')": 2, "('power', 'construct', 'roads')": 2, "('order', 'facilitate,', 'promote,')": 2, "('improve', 'navigation', 'water')": 2, "('construct', 'roads', 'canals,')": 2, "('common', 'defense', 'general')": 2, "('commerce', 'among', 'several')": 2, "('canals,', 'improve', 'navigation')": 2, "('General', 'State', 'Governments,')": 2, "('\"provide', 'common', 'defense')": 2, "('would', 'still', 'leave')": 1, "('would', 'left', 'constructive')": 1, "('would', 'effect', 'subjecting')": 1, "('would', 'effect', 'giving')": 1, "('would', 'effect', 'excluding')": 1, "('would', 'contrary', 'established')": 1, "('without', 'latitude', 'construction')": 1, "('without', 'inadmissible', 'latitude')": 1, "('within', 'purview', 'legislative')": 1, "('within', 'power', 'make')": 1, "('within', 'legislative', 'power')": 1, "('withhold', 'signature,', 'cherishing')": 1}}, "Abraham Lincoln": {"unigram": {"('war',)": 8, "('shall',)": 5, "('let',)": 4, "('Union',)": 4, "('years',)": 3, "('would',)": 3, "('war,',)": 3, "('us',)": 3, "('must',)": 3, "('may',)": 3, "('interest',)": 3, "('God',)": 3, "('woe',)": 2, "('without',)": 2, "('wills',)": 2, "('still',)": 2, "('said',)": 2, "('rather',)": 2, "('one',)": 2, "('offense',)": 2, "('occasion',)": 2, "('needs',)": 2, "('less',)": 2, "('gives',)": 2, "('four',)": 2}, "bigram": {"('war', 'rather')": 2, "('rather', 'let')": 2, "('must', 'needs')": 2, "('let', 'us')": 2, "('years,', 'public')": 1, "('years', 'unrequited')": 1, "('years', 'ago,')": 1, "('years', 'ago')": 1, "('wringing', 'bread')": 1, "('wounds,', 'care')": 1, "('would', 'rend')": 1, "('would', 'make')": 1, "('would', 'accept')": 1, "('world', 'offenses;')": 1, "('work,', 'bind')": 1, "('woe', 'man')": 1, "('woe', 'due')": 1, "('without', 'war-seeking')": 1, "('without', 'war,')": 1, "('wills', 'remove,')": 1, "('wills', 'continue')": 1, "('widow', 'orphan,')": 1, "('whole', 'population')": 1, "('well', 'known')": 1, "('wealth', 'piled')": 1}, "trigram": {"('war', 'rather', 'let')": 2, "('years,', 'public', 'declarations')": 1, "('years', 'unrequited', 'toil')": 1, "('years', 'ago,', 'still')": 1, "('years', 'ago', 'thoughts')": 1, "('wringing', 'bread', 'sweat')": 1, "('wounds,', 'care', 'shall')": 1, "('would', 'rend', 'Union')": 1, "('would', 'make', 'war')": 1, "('would', 'accept', 'war')": 1, "('world', 'offenses;', 'must')": 1, "('work,', 'bind', \"nation's\")": 1, "('woe', 'man', 'offense')": 1, "('woe', 'due', 'offense')": 1, "('without', 'war-seeking', 'dissolve')": 1, "('without', 'war,', 'insurgent')": 1, "('wills', 'remove,', 'gives')": 1, "('wills', 'continue', 'wealth')": 1, "('widow', 'orphan,', 'may')": 1, "('whole', 'population', 'colored')": 1, "('well', 'known', 'public,,')": 1, "('wealth', 'piled', \"bondsman's\")": 1, "('war-seeking', 'dissolve', 'Union')": 1, "('war,', 'one', 'would')": 1, "('war,', 'insurgent', 'agents')": 1}}, "Thomas Jefferson": {"unigram": {"('life,',)": 3, "('duties',)": 3, "('whose',)": 2, "('received',)": 2, "('public',)": 2, "('private',)": 2, "('neighbors,',)": 2, "('fellow',)": 2, "('called,',)": 2, "('younger',)": 1, "('world,?',)": 1, "('wonderful',)": 1, "('witnesses',)": 1, "('wishes',)": 1, "('welfare',)": 1, "('welcome',)": 1, "('watchful',)": 1, "('vicinage',)": 1, "('verdict',)": 1, "('various',)": 1, "('us,',)": 1, "('turmoil,',)": 1, "('triers',)": 1, "('tranquil',)": 1, "('therewith??',)": 1}, "bigram": {"('private', 'life,')": 2, "('younger', 'abler')": 1, "('world,?', 'whose')": 1, "('wonderful', 'era')": 1, "('witnesses', 'observers,')": 1, "('wishes', 'happiness')": 1, "('whose', 'ox')": 1, "('whose', 'hand')": 1, "('welfare', 'prosperity.')": 1, "('welcome', 'good')": 1, "('watchful', 'cares,')": 1, "('vicinage', '.,')": 1, "('verdict', 'rest')": 1, "('various', 'duties')": 1, "('us,', 'sweetener')": 1, "('turmoil,', 'bustle')": 1, "('triers', 'vicinage')": 1, "('tranquil', 'irresponsible')": 1, "('therewith??', 'verdict')": 1, "('theatre', 'public')": 1, "('testimony', 'native')": 1, "('taken,', 'defrauded?')": 1, "('sweetener', 'every')": 1, "('submit:', 'testimony')": 1, "('stations', 'called,')": 1}, "trigram": {"('younger', 'abler', 'minds')": 1, "('world,?', 'whose', 'ox')": 1, "('wonderful', 'era', 'made')": 1, "('witnesses', 'observers,', 'triers')": 1, "('wishes', 'happiness', 'received')": 1, "('whose', 'ox', 'taken,')": 1, "('whose', 'hand', 'received')": 1, "('welcome', 'good', 'give')": 1, "('watchful', 'cares,', 'labors,')": 1, "('vicinage', '.,', 'neighbors,')": 1, "('verdict', 'rest', 'conscious')": 1, "('various', 'duties', 'relations,')": 1, "('us,', 'sweetener', 'every')": 1, "('turmoil,', 'bustle', 'splendor')": 1, "('triers', 'vicinage', '.,')": 1, "('tranquil', 'irresponsible', 'occupations')": 1, "('therewith??', 'verdict', 'rest')": 1, "('theatre', 'public', 'life,;')": 1, "('testimony', 'native', 'country,')": 1, "('taken,', 'defrauded?', 'oppressed,')": 1, "('sweetener', 'every', 'hour')": 1, "('submit:', 'testimony', 'native')": 1, "('stations', 'called,', 'obtained')": 1, "('splendor', 'office,', 'drawn')": 1, "('society', 'raised,', 'ever')": 1}}, "John Adams": {"unigram": {"('may',)": 8, "('public',)": 7, "('United',)": 7, "('great',)": 6, "('States',)": 6, "('us',)": 5, "('protection',)": 5, "('Gentlemen',)": 5, "('Congress',)": 5, "('present',)": 4, "('country',)": 4, "('yet',)": 3, "('wisdom',)": 3, "('treaty',)": 3, "('shall',)": 3, "('session',)": 3, "('resources',)": 3, "('ought',)": 3, "('laws',)": 3, "('last',)": 3, "('gentlemen,',)": 3, "('future',)": 3, "('experience',)": 3, "('considerable',)": 3, "('commerce',)": 3}, "bigram": {"('United', 'States')": 6, "('House', 'Representatives:')": 3, "('Gentlemen', 'House')": 3, "('last', 'session')": 2, "('Senate', 'Gentlemen')": 2, "('Gentlemen', 'Senate')": 2, "('zealous', 'cooperation.')": 1, "('yet', 'removed')": 1, "('yet', 'hoped')": 1, "('yet', 'great')": 1, "('year,', 'together')": 1, "('year', 'considerable')": 1, "('would', 'unbecoming')": 1, "('world', 'experience')": 1, "('works', 'remain')": 1, "('without', 'looking')": 1, "('without', 'committing')": 1, "('within', 'energies')": 1, "('within', 'United')": 1, "('wished,', 'yet')": 1, "('wise', 'true')": 1, "('wisdom', 'magnanimity,')": 1, "('wisdom', 'efficiency')": 1, "('wisdom', 'avoid')": 1, "('whose', 'name')": 1}, "trigram": {"('Gentlemen', 'House', 'Representatives:')": 3, "('Senate', 'Gentlemen', 'House')": 2, "('Gentlemen', 'Senate', 'Gentlemen')": 2, "('yet', 'hoped', 'efforts')": 1, "('yet', 'great', 'reason')": 1, "('year,', 'together', 'account')": 1, "('year', 'considerable', 'former')": 1, "('would', 'unbecoming', 'representatives')": 1, "('world', 'experience', 'admonish')": 1, "('works', 'remain', 'incomplete')": 1, "('without', 'looking', 'Supreme')": 1, "('without', 'committing', 'dangerous')": 1, "('within', 'energies', 'resources,')": 1, "('within', 'United', 'States')": 1, "('wished,', 'yet', 'great')": 1, "('wise', 'true', 'economy')": 1, "('wisdom', 'magnanimity,', 'constancy')": 1, "('wisdom', 'efficiency', 'measures')": 1, "('wisdom', 'avoid', 'causes')": 1, "('whose', 'name', 'bears')": 1, "('whether', 'local', 'powers')": 1, "('whether', 'additional', 'appropriations')": 1, "('wealth,', 'population,', 'possessing')": 1, "('war,', 'may', 'case')": 1, "('virtue,', 'wisdom', 'magnanimity,')": 1}}, "George Washington": {"unigram": {"('United',)": 16, "('public',)": 11, "('may',)": 10, "('shall',)": 7, "('States,',)": 7, "('States',)": 7, "('would',)": 6, "('without',)": 6, "('time',)": 6, "('part',)": 6, "('War,',)": 6, "('Treaty',)": 6, "('National',)": 6, "('present',)": 5, "('object',)": 5, "('much',)": 5, "('last',)": 5, "('every',)": 5, "('Nation',)": 5, "('Military',)": 5, "('Great',)": 5, "('Government',)": 5, "('Commissioners',)": 5, "('Citizens',)": 5, "('Britain,',)": 5}, "bigram": {"('United', 'States,')": 7, "('United', 'States')": 7, "('Great', 'Britain,')": 5, "('part', 'United')": 3, "('appointed', 'part')": 3, "('House', 'Representatives:')": 3, "('time', 'War,')": 2, "('running', 'boundary')": 2, "('reside', 'Great')": 2, "('public', 'account,')": 2, "('may', 'even')": 2, "('last', 'Session,')": 2, "('insure', 'continuance')": 2, "('carrying', 'effect')": 2, "('West', 'Indies,')": 2, "('United', 'States;')": 2, "('Posts', 'within')": 2, "('Naval', 'force')": 2, "('Commissioners', 'appointed')": 2, "('Catholic', 'Majesty')": 2, "('Article', 'Treaty')": 2, "('zealous', 'attention')": 1, "('yield', 'surplus')": 1, "('yet', 'sufficiently')": 1, "('yet', 'fully')": 1}, "trigram": {"('appointed', 'part', 'United')": 3, "('reside', 'Great', 'Britain,')": 2, "('part', 'United', 'States,')": 2, "('Commissioners', 'appointed', 'part')": 2, "('zealous', 'attention', 'present')": 1, "('yield', 'surplus', 'supply')": 1, "('yet', 'sufficiently', 'secured')": 1, "('yet', 'fully', 'ascertained;')": 1, "('yet', 'communication', 'Commissioners')": 1, "('year,', 'submitted', 'proper')": 1, "('would', 'seem', 'trade')": 1, "('would', 'repugnant', 'vital')": 1, "('would', 'impair', 'energy')": 1, "('would', 'hazard', 'safety,')": 1, "('would', 'excellent', 'auxiliaries')": 1, "('would', 'admit,', 'carried')": 1, "('without', 'success,', 'directed')": 1, "('without', 'protecting', 'force,')": 1, "('without', 'inconvenience;', 'future')": 1, "('without', 'delay,', 'provide,')": 1, "('without', 'adequate', 'stock')": 1, "('without', 'accomplished;', 'Nation,')": 1, "('within,', 'selection', 'Characters')": 1, "('within', 'period', 'withdrawn')": 1, "('within', 'limits', 'United')": 1}}, "Barack Obama": {"unigram": {"('(Applause',)": 39, "('.)',)": 38, "('America',)": 13, "('us',)": 11, "('country',)": 10, "('work',)": 8, "('future',)": 8, "('every',)": 8, "('forward',)": 7, "('never',)": 6, "('ever',)": 6, "('best',)": 6, "('want',)": 5, "('one',)": 5, "('new',)": 5, "('nation',)": 5, "('President',)": 5, "(\".'s\",)": 5, "('young',)": 4, "('voice',)": 4, "('together,',)": 4, "('seen',)": 4, "('politics',)": 4, "('moves',)": 4, "('makes',)": 4}, "bigram": {"('(Applause', '.)')": 37, "('moves', 'forward')": 3, "('United', 'States')": 3, "('.)', 'want')": 3, "('would', 'rather')": 2, "('want', 'thank')": 2, "('rather', 'cut')": 2, "('never', 'hopeful')": 2, "('need', 'go')": 2, "('move', 'country')": 2, "('makes', 'us')": 2, "('makes', 'America')": 2, "('make', 'sure')": 2, "('every', 'American')": 2, "('country', 'forward')": 2, "('God', 'bless')": 2, "('.)', 'Whether')": 2, "('.)', 'Tonight,')": 2, "(\".'s\", 'always')": 2, "('(Applause', \".)'s\")": 2, "('\u2019,', 'despite')": 1, "('young', 'women,')": 1, "('young', 'old,')": 1, "('young', 'field')": 1, "('young', 'boy')": 1}, "trigram": {"('(Applause', '.)', 'want')": 3, "('would', 'rather', 'cut')": 2, "('move', 'country', 'forward')": 2, "('.)', 'want', 'thank')": 2, "('(Applause', '.)', 'Whether')": 2, "('(Applause', '.)', 'Tonight,')": 2, "('\u2019,', 'despite', 'frustrations')": 1, "('young', 'women,', 'like')": 1, "('young', 'old,', 'rich')": 1, "('young', 'field', 'organizer')": 1, "('young', 'boy', 'South')": 1, "('years', 'former', 'colony')": 1, "('wreckage', 'terrible', 'storm')": 1, "('world;', 'nation', 'defended')": 1, "('world', 'live', 'greatest')": 1, "('world', 'ever', 'known--(applause)--also')": 1, "('world', 'coming', 'shores')": 1, "('works', 'accept', 'certain')": 1, "('working,', 'keep', 'fighting')": 1, "('working', 'phones', 'late')": 1, "('working', 'leaders', 'parties')": 1, "('working', 'late', 'campaign')": 1, "('workers', 'would', 'rather')": 1, "('worked', 'way', 'college,')": 1, "('work,', 'future', 'lies')": 1}}, "George W. Bush": {"unigram": {"('people',)": 45, "('THE',)": 35, "('PRESIDENT:',)": 35, "('Q',)": 30, "('going',)": 29, "('know,',)": 28, "(\".'s\",)": 28, "('would',)": 20, "('like',)": 18, "('got',)": 17, "('get',)": 17, "('one',)": 16, "('lot',)": 16, "('think',)": 15, "('best',)": 15, "('President',)": 14, "(\".n't\",)": 14, "('.,',)": 14, "('.)',)": 13, "('made',)": 12, "('Mr.',)": 12, "('make',)": 11, "('different',)": 11, "(\".'m\",)": 11, "('(Laughter',)": 11}, "bigram": {"('THE', 'PRESIDENT:')": 29, "('(Laughter', '.)')": 11, "('.)', 'Q')": 8, "('wish', 'best')": 6, "('Mr.', 'President,')": 6, "('New', 'Orleans')": 5, "('Mr.', 'President')": 5, "('sustainable', 'cease-fire')": 4, "('Thank,', 'Mr.')": 4, "('Social', 'Security')": 4, "('Q', 'Thank,')": 4, "('Q', 'Mr.')": 4, "('President-Elect', 'Obama')": 4, "('PRESIDENT:', 'Yes')": 4, "('years', 'ago,')": 3, "('tax', 'cuts')": 3, "('said,', 'well,')": 3, "('moral', 'standing')": 3, "('know,', 'people')": 3, "('going', 'feel')": 3, "('federal', 'response')": 3, "('decisions', 'made')": 3, "('could', 'done')": 3, "('best', 'way')": 3, "('Wall', 'Street')": 3}, "trigram": {"('(Laughter', '.)', 'Q')": 8, "('Thank,', 'Mr.', 'President')": 4, "('Q', 'Thank,', 'Mr.')": 4, "('THE', 'PRESIDENT:', 'Yes')": 3, "('Q', 'Mr.', 'President,')": 3, "('war', 'Iraq', 'without')": 2, "('time', 'leave', 'office?')": 2, "('third', 'rail', 'American')": 2, "('roofs', 'right', 'storm')": 2, "('rail', 'American', 'politics')": 2, "('pulled', 'roofs', 'right')": 2, "('people', 'pulled', 'roofs')": 2, "('moral', 'standing', 'world')": 2, "(\"know's\", 'going', 'feel')": 2, "('highly', 'enriched', 'uranium')": 2, "('harsh', 'interrogation', 'tactics')": 2, "('federal', 'response', 'slow')": 2, "('enemy', 'would', 'like')": 2, "('THE', 'PRESIDENT:', 'know,')": 2, "('THE', 'PRESIDENT:', 'hope')": 2, "('THE', 'PRESIDENT:', 'Well,')": 2, "('THE', 'PRESIDENT:', 'Thank')": 2, "('President,', 'spoke', 'moment')": 2, "('Mr.', 'President,', 'spoke')": 2, "(\"America's\", 'moral', 'standing')": 2}}, "Bill Clinton": {"unigram": {"('world',)": 10, "('America',)": 9, "('must',)": 8, "('global',)": 7, "('people',)": 6, "('new',)": 6, "('million',)": 6, "('every',)": 6, "('Americans',)": 6, "('work',)": 5, "('ever',)": 5, "('us',)": 4, "('live',)": 4, "('future',)": 4, "('around',)": 4, "('President',)": 4, "('years',)": 3, "('time',)": 3, "('record',)": 3, "('peace',)": 3, "('leave',)": 3, "('lead',)": 3, "('last',)": 3, "('higher',)": 3, "('grateful',)": 3}, "bigram": {"('million', 'Americans')": 3, "('around', 'world')": 3, "('work', 'harder')": 2, "('must', 'work')": 2, "('lead', 'world')": 2, "('global', 'economy')": 2, "('force', 'peace')": 2, "('billions', 'around')": 2, "('United', 'States')": 2, "('America', 'must')": 2, "('America', 'force')": 2, "(\".'m\", 'grateful')": 2, "('years,', 'highest')": 1, "('years', 'ahead,')": 1, "('world', 'unless')": 1, "('world', 'look')": 1, "('world', 'live')": 1, "('world', 'embody')": 1, "('world', 'connected')": 1, "('world', 'chance')": 1, "('work', 'prepare')": 1, "('work', 'live')": 1, "('work', 'done')": 1, "('word', 'deed')": 1, "('wishing', 'best')": 1}, "trigram": {"('must', 'work', 'harder')": 2, "('billions', 'around', 'world')": 2, "('America', 'force', 'peace')": 2, "('years,', 'highest', 'homeownership')": 1, "('years', 'ahead,', 'never')": 1, "('world', 'unless', 'home')": 1, "('world', 'look', 'America')": 1, "('world', 'live', \"knife's\")": 1, "('world', 'embody', 'shared')": 1, "('world', 'connected', 'every')": 1, "('world', 'chance', 'work')": 1, "('work', 'prepare', 'Nation')": 1, "('work', 'live', 'raise')": 1, "('work', 'harder', 'unite')": 1, "('work', 'harder', 'overcome')": 1, "('work', 'done', 'President\u2014every')": 1, "('word', 'deed', 'put')": 1, "('wishing', 'best', 'next')": 1, "('wisely,', 'pay', 'debt,')": 1, "('weave', 'threads', 'coat')": 1, "('wear', 'proudly', 'citizens')": 1, "('weapons', 'disease,', 'degradation')": 1, "('way,', \"America's\", 'security')": 1, "('wars', '20th', 'century,')": 1, "('warned', 'entangling', 'alliances')": 1}}, "George H. W. Bush": {"unigram": {"('force',)": 23, "('military',)": 19, "('one',)": 16, "('world',)": 14, "('United',)": 14, "('must',)": 12, "('States',)": 12, "('could',)": 11, "('would',)": 10, "('use',)": 10, "('new',)": 9, "('American',)": 9, "('many',)": 8, "('important',)": 8, "('General',)": 8, "('country',)": 7, "('.,',)": 7, "('women',)": 6, "('way',)": 6, "('others',)": 6, "('never',)": 6, "('made',)": 6, "('day',)": 6, "('U.S.',)": 6, "('Leadership',)": 6}, "bigram": {"('United', 'States')": 12, "('new', 'world')": 7, "('military', 'force')": 7, "('men', 'women')": 5, "('use', 'military')": 4, "('use', 'force')": 4, "('using', 'force')": 3, "('half', 'century')": 3, "('Good', 'luck')": 3, "('Armed', 'Forces')": 3, "('world', 'order,')": 2, "('willingness', 'accept')": 2, "('using', 'military')": 2, "('use', 'force,')": 2, "('served', 'country')": 2, "('passed', 'since')": 2, "('order,', 'one')": 2, "('must', 'lead')": 2, "('many', 'forms')": 2, "('friends', 'allies')": 2, "('force', 'makes')": 2, "('far', 'better')": 2, "('every', 'case')": 2, "('end', 'cold')": 2, "('cold', 'war,')": 2}, "trigram": {"('use', 'military', 'force')": 4, "('world', 'order,', 'one')": 2, "('using', 'military', 'force')": 2, "('new', 'world', 'order,')": 2, "('half', 'century', 'passed')": 2, "('century', 'passed', 'since')": 2, "('U.N.', 'Security', 'Council')": 2, "('young', 'men', 'women')": 1, "('young', 'marine,', 'eyes')": 1, "('years,', 'somewhere,', 'General')": 1, "('years,', 'men', 'women')": 1, "('years', 'still', 'made,')": 1, "('years', 'ago,', 'another')": 1, "('would-be', 'troublemakers', 'blueprint')": 1, "('would', 'single', 'particular')": 1, "('would', 'risk', 'emergence')": 1, "('would', 'possible', 'cold')": 1, "('would', 'like', 'find')": 1, "('would', 'guarantee', 'mistakes')": 1, "('would', 'give', 'would-be')": 1, "('would', 'exhaust', 'process,')": 1, "('would', 'desired', 'effect,')": 1, "('would', 'concede,', 'blessing')": 1, "('worthy', 'goals,', 'persuading')": 1, "('world,', 'one', 'far')": 1}}, "Jimmy Carter": {"unigram": {"('world',)": 12, "('people',)": 11, "('human',)": 10, "('must',)": 9, "('President',)": 8, "('American',)": 8, "('future',)": 7, "('rights',)": 6, "('nuclear',)": 6, "('home',)": 6, "('first',)": 6, "('difficult',)": 6, "('us',)": 5, "('political',)": 5, "('every',)": 5, "('common',)": 5, "('United',)": 5, "('Nation',)": 5, "('would',)": 4, "('vision',)": 4, "('time',)": 4, "('support',)": 4, "('special',)": 4, "('responsibility',)": 4, "('one',)": 4}, "bigram": {"('United', 'States')": 4, "('human', 'rights')": 3, "('work', 'hard')": 2, "('last', '4')": 2, "('human', 'rights,')": 2, "('generation', 'must')": 2, "('every', 'American')": 2, "('difficult', 'times')": 2, "('World', 'War')": 2, "('War', 'II')": 2, "('4', 'years')": 2, "('yield', 'temptation')": 1, "('yet,', 'thank')": 1, "('yet', 'happen,')": 1, "('years,', 'wish')": 1, "('years', 'since')": 1, "('years', 'office,')": 1, "('years', 'made')": 1, "('year', '2000')": 1, "('would', 'unleashed')": 1, "('would', 'take')": 1, "('would', 'live')": 1, "('would', 'like')": 1, "('world\u2014water,', 'food,')": 1, "('world:', 'decent')": 1}, "trigram": {"('World', 'War', 'II')": 2, "('yet,', 'thank', 'God,')": 1, "('yet', 'happen,', 'hope')": 1, "('years,', 'wish', 'say')": 1, "('years', 'since', 'first')": 1, "('years', 'office,', 'others,')": 1, "('years', 'made', 'certain')": 1, "('year', '2000', 'much')": 1, "('would', 'unleashed', 'every')": 1, "('would', 'take', 'missiles')": 1, "('would', 'live', 'despair')": 1, "('would', 'like', 'first')": 1, "('world\u2014water,', 'food,', 'minerals,')": 1, "('world:', 'decent', 'education')": 1, "(\"world's\", 'people', 'remember')": 1, "('world', 'year', '2000')": 1, "('world', 'within', 'live')": 1, "('world', 'three', 'issues,')": 1, "('world', 'stockpiles', 'nuclear')": 1, "('world', 'leaders', 'concern')": 1, "('world', 'founded', 'explicitly')": 1, "('world', 'either', 'nourish')": 1, "('world', 'difficult', 'times')": 1, "('world', 'among', 'severely')": 1, "('worked', 'office', 'President,')": 1}}, "Gerald Ford": {"unigram": {"('new',)": 18, "('President',)": 18, "('energy',)": 17, "('Congress',)": 17, "('peace',)": 15, "('years',)": 14, "('must',)": 14, "('federal',)": 13, "('government',)": 12, "('defense',)": 12, "('Union',)": 12, "('people',)": 11, "('world',)": 10, "('today',)": 10, "('strategic',)": 10, "('many',)": 10, "('year',)": 9, "('state',)": 9, "('national',)": 9, "('free',)": 9, "('economic',)": 9, "('United',)": 9, "('well',)": 8, "('us',)": 8, "('report',)": 8}, "bigram": {"('state', 'Union')": 8, "('United', 'States')": 5, "('third', 'century')": 4, "('years', 'ago')": 3, "('new', 'administration')": 3, "('new', 'President')": 3, "('national', 'defense')": 3, "('many,', 'many')": 3, "('energy', 'independence')": 3, "('Vice', 'President')": 3, "('United', 'States,')": 3, "('Middle', 'East')": 3, "('upon', 'foreign')": 2, "('two', 'years')": 2, "('strategic', 'nuclear')": 2, "('strategic', 'forces')": 2, "('strategic', 'balance')": 2, "('solid', 'foundation')": 2, "('security', 'needs')": 2, "('say', 'half')": 2, "('report', 'state')": 2, "('report', 'national')": 2, "('remain', 'first')": 2, "('permanent', 'jobs')": 2, "('peace', 'Middle')": 2}, "trigram": {"('state', 'Union', 'good')": 2, "('report', 'state', 'Union')": 2, "('report', 'national', 'defense')": 2, "('peace', 'Middle', 'East')": 2, "('national', 'security', 'needs')": 2, "('Vice', 'President', 'President')": 2, "('Two', 'years', 'ago')": 2, "('\u2014but', 'Union', 'first')": 1, "('you\u2014particularly', 'new', 'members\u2014as')": 1, "('yet', 'Soviet', 'Union')": 1, "('years\u2014I', 'say', 'confidence')": 1, "('years,', 'result', 'decisions')": 1, "('years,', 'able', 'reverse')": 1, "('years', 'proved,', 'said')": 1, "('years', 'maintain', 'capabilities')": 1, "('years', 'freely', 'elected')": 1, "('years', 'free', \"world's\")": 1, "('years', 'domestic', 'spending')": 1, "('years', 'ago,', 'half,')": 1, "('years', 'ago', 'proposed')": 1, "('years', 'ago', 'freshman')": 1, "('years', 'ago', 'crime')": 1, "('year', 'year', 'vital')": 1, "('year', 'vital', 'matter;')": 1, "('year', 'open', 'floodgates')": 1}}, "Andrew Johnson": {"unigram": {"('States',)": 45, "('United',)": 38, "('Government',)": 38, "('upon',)": 36, "('year',)": 32, "('per',)": 29, "('people',)": 28, "('would',)": 27, "('national',)": 20, "('made',)": 20, "('may',)": 19, "('expenditures',)": 19, "('amount',)": 19, "('public',)": 18, "('last',)": 18, "('Congress',)": 18, "('years',)": 17, "('three',)": 17, "('cent',)": 17, "('hundred',)": 16, "('currency',)": 16, "('war',)": 15, "('time',)": 15, "('paper',)": 15, "('Secretary',)": 14}, "bigram": {"('United', 'States')": 32, "('per', 'cent')": 17, "('year', 'ending')": 10, "('fiscal', 'year')": 10, "('&', '#39;')": 10, "('ending', 'June')": 8, "('June', '30,')": 8, "('three', 'hundred')": 7, "('gold', 'silver')": 7, "('United', 'States,')": 6, "('Secretary', 'Treasury')": 6, "('Great', 'Britain')": 6, "('three', 'years')": 5, "('6', 'per')": 5, "('report', 'Secretary')": 4, "('precious', 'metals')": 4, "('per', 'cent,')": 4, "('per', 'capita')": 4, "('hundred', 'millions')": 4, "('circulating', 'medium')": 4, "('30th', 'June,')": 4, "('30,', '1868,')": 4, "('upon', 'question')": 3, "('treaty', 'United')": 3, "('rights', 'naturalized')": 3}, "trigram": {"('ending', 'June', '30,')": 8, "('year', 'ending', 'June')": 7, "('fiscal', 'year', 'ending')": 7, "('June', '30,', '1868,')": 4, "('6', 'per', 'cent')": 4, "('treaty', 'United', 'States')": 3, "('three', 'hundred', 'seventy-two')": 3, "('United', 'States', 'Great')": 3, "('States', 'Great', 'Britain')": 3, "('year', 'ending', '30th')": 2, "('two', 'Republics', 'island')": 2, "('seven', 'hundred', 'millions')": 2, "('rights', 'naturalized', 'citizens')": 2, "('public', 'expenditures', 'reached')": 2, "('per', 'cent,', 'increase')": 2, "('past', 'three', 'years')": 2, "('nation', '&', '#39;')": 2, "('millions,', 'three', 'hundred')": 2, "('man', '&', '#39;')": 2, "('late', 'United', 'States')": 2, "('last', 'fiscal', 'year')": 2, "('island', 'St.', 'Domingo')": 2, "('hundred', 'seventy-two', 'millions,')": 2, "('hundred', 'fifty', 'millions')": 2, "('equal', '9', 'per')": 2}}, "Ronald Reagan": {"unigram": {"('people',)": 14, "('America',)": 13, "('years',)": 11, "('way',)": 11, "('still',)": 11, "('one',)": 11, "('great',)": 11, "('American',)": 11, "('.,',)": 11, "(\".'s\",)": 11, "('.\"',)": 11, "(\".'ve\",)": 10, "('us',)": 9, "('past',)": 9, "('freedom',)": 9, "('city',)": 9, "('Well,',)": 9, "('back',)": 8, "('new',)": 7, "('made',)": 7, "('like',)": 7, "('government',)": 7, "('free',)": 7, "('economic',)": 7, "('could',)": 7}, "bigram": {"('eight', 'years')": 4, "(\".'s\", 'still')": 4, "('years', 'ago')": 3, "('past', 'eight')": 3, "('Soviet', 'Union')": 3, "('.\"', 'Well,')": 3, "('would', 'cause')": 2, "('went', 'politics')": 2, "('told', 'us')": 2, "(\"things'm\", 'proudest')": 2, "('sense', 'patriotism')": 2, "('right', 'thing')": 2, "('opening', 'meeting')": 2, "('new', 'closeness')": 2, "('never', 'saw')": 2, "('men', 'women')": 2, "('made', 'difference')": 2, "('made', 'city')": 2, "('get', 'sense')": 2, "('freedom', 'man')": 2, "('could', 'get')": 2, "('continue', 'work')": 2, "('continue', 'act')": 2, "('across', 'America')": 2, "('President', 'Gorbachev')": 2}, "trigram": {"('past', 'eight', 'years')": 2, "('get', 'sense', 'patriotism')": 2, "('could', 'get', 'sense')": 2, "('young,', 'smart,', 'fiercely')": 1, "('young', 'woman', 'writing')": 1, "('yet,', 'past', 'years,')": 1, "('yelled,', '\"Hello,', 'American')": 1, "('years:', 'resurgence', 'national')": 1, "('years,', 'two', 'centuries,')": 1, "('years,', \"soon'll\", 'time')": 1, "('years,', 'forged', 'satisfying')": 1, "('years', 'world', 'again\u2014and')": 1, "('years', 'work', 'brought')": 1, "('years', 'weakness', 'confusion')": 1, "('years', 'meant', 'mean')": 1, "('years', 'later,', 'another')": 1, "('years', 'come', '.\"')": 1, "('years', 'ago', 'reflects')": 1, "('years', 'ago', '40th')": 1, "('years', 'ago', '.:')": 1, "('years', 'age', 'grew')": 1, "('yearns', 'peace,', 'government')": 1, "('year,', 'began', 'actions')": 1, "('wrote', 'letter,', \"couldn't\")": 1, "('wrote', 'describe', 'America')": 1}}, "Dwight D. Eisenhower": {"unigram": {"('must',)": 10, "('peace',)": 8, "('military',)": 7, "('every',)": 7, "('balance',)": 6, "('world',)": 5, "('new',)": 5, "('may',)": 5, "('great',)": 5, "('free',)": 5, "('war',)": 4, "('toward',)": 4, "('shall',)": 4, "('people',)": 4, "('national',)": 4, "('human',)": 4, "('could',)": 4, "('come',)": 4, "('become',)": 4, "('among',)": 4, "('years',)": 3, "('upon',)": 3, "('together',)": 3, "('service',)": 3, "('research',)": 3}, "bigram": {"('peace', 'human')": 2, "('military', 'establishment')": 2, "('human', 'betterment')": 2, "('could', 'become')": 2, "('armaments', 'industry')": 2, "('United', 'States')": 2, "('Federal', 'government')": 2, "('yet', 'written')": 1, "('yet', 'realize')": 1, "('years--wish', 'could')": 1, "('years', 'past')": 1, "('years', 'blessed')": 1, "('yearn', 'freedom')": 1, "('written', 'America')": 1, "('would', 'unworthy')": 1, "('would', 'inflict')": 1, "('worthy;', 'rest,')": 1, "('world,', 'give')": 1, "('world,', 'ever')": 1, "('world', 'peace')": 1, "('world', 'conflicts,')": 1, "('world', 'advance')": 1, "('women', 'directly')": 1, "('witnessed', 'horror')": 1, "('witnessed', 'four')": 1}, "trigram": {"('peace', 'human', 'betterment')": 2, "('yet', 'written', 'America')": 1, "('yet', 'realize', \"America's\")": 1, "('years--wish', 'could', 'say')": 1, "('years', 'past', 'midpoint')": 1, "('years', 'blessed', 'peace')": 1, "('yearn', 'freedom', 'may')": 1, "('written', 'America', 'knows')": 1, "('would', 'unworthy', 'free')": 1, "('would', 'inflict', 'upon')": 1, "('worthy;', 'rest,', 'know')": 1, "('world,', 'give', 'expression')": 1, "('world,', 'ever', 'growing')": 1, "('world', 'peace', 'human')": 1, "('world', 'conflicts,', 'United')": 1, "('world', 'advance', 'along')": 1, "('women', 'directly', 'engaged')": 1, "('witnessed', 'horror', 'lingering')": 1, "('witnessed', 'four', 'major')": 1, "('without', 'risking', 'loss')": 1, "('without', 'complaint', 'burdens')": 1, "('within', 'principles', 'democratic')": 1, "('wish', 'new', 'President,')": 1, "('wise', 'resolution', 'better')": 1, "('whole', 'attention,', 'absorbs')": 1}}, "Richard M. Nixon": {"unigram": {"('always',)": 14, "('man',)": 8, "('think',)": 7, "('proud',)": 7, "('many',)": 7, "('great',)": 7, "('good',)": 7, "('young',)": 6, "('would',)": 6, "('want',)": 6, "('serve',)": 6, "('say',)": 6, "('one',)": 6, "('never',)": 6, "('know',)": 6, "('years',)": 5, "('life',)": 5, "('know,',)": 5, "('come',)": 5, "('White',)": 5, "('us',)": 4, "('things',)": 4, "('strong',)": 4, "('sometimes',)": 4, "('something',)": 4}, "bigram": {"('far', 'important')": 4, "('White', 'House')": 4, "('man', 'woman')": 3, "('important', 'numbers')": 3, "('every', 'one,')": 3, "('would', 'like')": 2, "('want', 'say')": 2, "('staff,', 'know,')": 2, "('serve', 'government')": 2, "('say', 'every')": 2, "('members', 'White')": 2, "('life', 'forever')": 2, "('lemon', 'ranch')": 2, "('last', 'night')": 2, "('greatness', 'comes')": 2, "('great,', 'great')": 2, "('always', 'remember,')": 2, "('\u2014and,', 'would')": 1, "('\u2014and', 'T.R')": 1, "('young', 'wife')": 1, "('young', 'people')": 1, "('young', 'must')": 1, "('young', 'man')": 1, "('young', 'lawyer')": 1, "('young', 'flower')": 1}, "trigram": {"('far', 'important', 'numbers')": 3, "('say', 'every', 'one,')": 2, "('members', 'White', 'House')": 2, "('\u2014and,', 'would', 'like')": 1, "('young', 'must', 'know;')": 1, "('young', 'lawyer', 'New')": 1, "('young', 'flower', 'died')": 1, "('yet,', 'always', 'come')": 1, "('years\u2014with', 'devotion', 'dedication,')": 1, "('years', 'seemed', 'bright,')": 1, "('years', 'old', 'older')": 1, "('years', 'Arizona,', 'seeing')": 1, "('wrong,', 'sometimes', 'right,')": 1, "('wrong', 'Administration,', 'top')": 1, "('writing', 'poor', 'bar')": 1, "('write', 'book,', 'probably,')": 1, "('would', 'say', 'mother\u2014my')": 1, "('would', 'love', 'talked')": 1, "('would', 'like', 'tell')": 1, "('would', 'like', 'recompense')": 1, "('would', 'called', 'sort')": 1, "('would', 'always', 'get')": 1, "('worse,', 'years', 'ahead')": 1, "('world\u2014everybody', 'wants', 'tell')": 1, "('world,', 'without', 'leadership,')": 1}}, "Harry S. Truman": {"unigram": {"('Democratic',)": 6, "('Congress',)": 6, "('people',)": 5, "('wonderful',)": 4, "('tell',)": 4, "('like',)": 4, "('history',)": 4, "('great',)": 4, "('farmer',)": 4, "('back',)": 4, "(\".'s\",)": 4, "('tried',)": 3, "('privilege',)": 3, "('price',)": 3, "('level',)": 3, "('got',)": 3, "('going',)": 3, "('go',)": 3, "('farmers',)": 3, "('chance',)": 3, "('cents',)": 3, "('candidate',)": 3, "('best',)": 3, "('appreciate',)": 3, "('United',)": 3}, "bigram": {"('tried', 'level')": 3, "('level', 'best')": 3, "('Congress', 'tried')": 3, "('whether', 'want')": 2, "('public', 'officials')": 2, "('price', 'support')": 2, "('people', 'made')": 2, "('let', 'chance')": 2, "('great', 'pleasure')": 2, "('candidate', 'Governor')": 2, "('best', 'put')": 2, "('United', 'States')": 2, "('Guy', 'Gillette')": 2, "('Democratic', 'candidate')": 2, "('Democratic', 'Party')": 2, "('80th', 'Congress')": 2, "(\".'s\", 'great')": 2, "('\"do-nothing\"', '80th')": 2, "(\"you\u2014you're\", 'going')": 1, "('years', 'kept')": 1, "('years', \".'s\")": 1, "('would', 'like')": 1, "('worth', 'price')": 1, "('world', 'alive')": 1, "('wonderful', 'turnout,')": 1}, "trigram": {"('tried', 'level', 'best')": 3, "('Congress', 'tried', 'level')": 3, "('level', 'best', 'put')": 2, "('Democratic', 'candidate', 'Governor')": 2, "(\".'s\", 'great', 'pleasure')": 2, "('\"do-nothing\"', '80th', 'Congress')": 2, "(\"you\u2014you're\", 'going', 'get')": 1, "('years', 'kept', 'millions')": 1, "('years', \".'s\", 'great')": 1, "('would', 'like', 'go')": 1, "('world', 'alive', \".'m\")": 1, "('wonderful', 'turnout,', 'wonderful')": 1, "('wonderful', 'tour', 'today')": 1, "('wonderful', 'reception', \".'s\")": 1, "('wonderful', 'man,', 'Democratic')": 1, "(\"won't\", 'sympathy', \".n't\")": 1, "(\"won't\", 'say', 'much')": 1, "('whole', 'history', 'country')": 1, "('whether', 'want', 'turn')": 1, "('whether', 'want', 'go')": 1, "('welfare', 'welfare', 'great')": 1, "('welfare', 'great', \"State,'ll\")": 1, "('wanted', 'take', 'town')": 1, "('want', 'turn', 'clock')": 1, "('want', 'go', 'forward')": 1}}, "Franklin D. Roosevelt": {"unigram": {"('world',)": 38, "('peace',)": 27, "('people',)": 18, "('Nations',)": 18, "('Germany',)": 18, "('German',)": 18, "('United',)": 17, "('Conference',)": 17, "('made',)": 16, "('Poland',)": 16, "('war',)": 15, "('one',)": 14, "('time',)": 13, "('three',)": 12, "('American',)": 12, "('think',)": 11, "('would',)": 10, "('us',)": 10, "('problems',)": 10, "('must',)": 10, "('military',)": 10, "('liberated',)": 10, "('know',)": 10, "('great',)": 10, "('Nazi',)": 10}, "bigram": {"('United', 'States')": 8, "('San', 'Francisco')": 6, "('world', 'peace')": 5, "('liberated', 'areas')": 5, "('Crimea', 'Conference')": 5, "('unconditional', 'surrender')": 4, "('peace', 'world')": 4, "('go', 'far')": 4, "('United', 'States,')": 4, "('Nations', 'world')": 4, "('International', 'Security')": 4, "('wanted,', 'certain')": 3, "('three', 'major')": 3, "('next', 'month')": 3, "('major', 'powers')": 3, "('joint', 'responsibility')": 3, "('independent,', 'prosperous')": 3, "('fighting', 'men')": 3, "('defeat', 'Germany')": 3, "('United', 'Nations')": 3, "('Senate', 'United')": 3, "('Security', 'Organization')": 3, "('Security', 'Council')": 3, "('German', 'people')": 3, "('German', 'militarism')": 3}, "trigram": {"('International', 'Security', 'Organization')": 3, "('wanted,', 'certain', 'areas;')": 2, "('voting', 'Security', 'Council')": 2, "('unconditional', 'surrender', 'mean')": 2, "('three', 'powerful', 'Nations')": 2, "('strong,', 'independent,', 'prosperous')": 2, "('rest', 'recreation', 'center')": 2, "('political', 'economic', 'problems')": 2, "('find', 'common', 'ground')": 2, "('certain', 'areas;', 'go')": 2, "('areas;', 'go', 'far')": 2, "('Senate', 'United', 'States,')": 2, "('San', 'Francisco', 'next')": 2, "('San', 'Francisco', 'Conference')": 2, "('Nazi', 'officers', 'took')": 2, "('Francisco', 'next', 'month')": 2, "('Constitution', 'United', 'States')": 2, "('\u2014with', '\"wars', '.\"')": 1, "('\u2014a', 'greater', 'facility')": 1, "('zones', 'coordinated', 'Berlin')": 1, "('zone', 'control', 'Germany,')": 1, "('zone', 'Germany\u2014and', 'administration')": 1, "('you\u2014and,', 'time,', 'people')": 1, "('yet\"', '\u2014with', '\"wars')": 1, "('yet', 'possible', 'announce')": 1}}, "Benjamin Harrison": {"unigram": {"('United',)": 10, "('States',)": 8, "('city',)": 4, "('within',)": 3, "('unlawful',)": 3, "('riotous',)": 3, "('part',)": 3, "('obstructions,',)": 3, "('laws',)": 3, "('combinations,',)": 3, "('assemblages',)": 3, "('State',)": 3, "('President',)": 3, "('warning',)": 2, "('taking',)": 2, "('property',)": 2, "('persons',)": 2, "('mob',)": 2, "('may',)": 2, "('hereby',)": 2, "('execution',)": 2, "('especially',)": 2, "('employed',)": 2, "('day',)": 2, "('Whereas,',)": 2}, "bigram": {"('United', 'States')": 8, "('unlawful', 'obstructions,')": 3, "('obstructions,', 'combinations,')": 3, "('laws', 'United')": 3, "('taking', 'part')": 2, "('riotous', 'mob')": 2, "('execution', 'laws')": 2, "('combinations,', 'assemblages')": 2, "('President', 'United')": 2, "('without', 'criminal')": 1, "('within', 'said')": 1, "('within', 'city')": 1, "('within', 'State')": 1, "('whereof', 'hereunto')": 1, "('way', 'connected')": 1, "('warning', 'persist')": 1, "('warning', 'especially')": 1, "('warn', 'persons')": 1, "('vacillation', 'decisive')": 1, "('unlawfully', 'participating')": 1, "('treatment', 'guilty,')": 1, "('therefore,,', 'Grover')": 1, "('therefore,', 'actually')": 1, "('testimony', 'whereof')": 1, "('stern', 'necessities')": 1}, "trigram": {"('unlawful', 'obstructions,', 'combinations,')": 3, "('laws', 'United', 'States')": 3, "('obstructions,', 'combinations,', 'assemblages')": 2, "('execution', 'laws', 'United')": 2, "('without', 'criminal', 'intent')": 1, "('within', 'said', 'State;')": 1, "('within', 'city', 'State')": 1, "('within', 'State', 'Illinois,')": 1, "('whereof', 'hereunto', 'set')": 1, "('way', 'connected', 'unlawful')": 1, "('warning', 'persist', 'taking')": 1, "('warning', 'especially', 'intended')": 1, "('warn', 'persons', 'engaged')": 1, "('vacillation', 'decisive', 'treatment')": 1, "('unlawfully', 'participating', 'abide')": 1, "('treatment', 'guilty,', 'warning')": 1, "('therefore,,', 'Grover', 'Cleveland,')": 1, "('therefore,', 'actually', 'unlawfully')": 1, "('testimony', 'whereof', 'hereunto')": 1, "('taking', 'part', 'unlawful')": 1, "('taking', 'part', 'riotous')": 1, "('stern', 'necessities', 'confront')": 1, "('set', 'hand', 'caused')": 1, "('seal', 'United', 'States')": 1, "('said', 'State;', 'Whereas,')": 1}}, "John F. Kennedy": {"unigram": {"('struggle',)": 8, "('free',)": 8, "('Cuba',)": 8, "('freedom',)": 7, "('clear',)": 6, "('time',)": 5, "('must',)": 5, "('intend',)": 5, "('country',)": 5, "('survival',)": 4, "('new',)": 4, "('forces',)": 4, "('fail',)": 4, "('every',)": 4, "('ever',)": 4, "('Cuban',)": 4, "('Communist',)": 4, "('would',)": 3, "('small',)": 3, "('refugees',)": 3, "('present',)": 3, "('people',)": 3, "('obligation',)": 3, "('nations',)": 3, "('nation',)": 3}, "bigram": {"('free', 'nations')": 3, "('dare', 'fail')": 3, "('small', 'band')": 2, "('nuclear', 'armaments')": 2, "('first', 'time')": 2, "('Revolutionary', 'Council,')": 2, "('young', 'Cubans')": 1, "('yet', 'spoken')": 1, "('yesterday,', 'involved')": 1, "('yearning', 'people')": 1, "('would', 'intervene')": 1, "('would', 'expect')": 1, "('would', 'contrary')": 1, "('worse', 'instead')": 1, "('world', 'possess')": 1, "('women', 'fighting')": 1, "('without', 'firing')": 1, "('without', 'fanfare,')": 1, "('wished', 'evacuated')": 1, "('whose', 'character')": 1, "('well', 'must')": 1, "('well', 'military--peril')": 1, "('ways', 'difficult')": 1, "('war,', 'disappointment')": 1, "('want', 'clearly')": 1}, "trigram": {"('young', 'Cubans', 'regain')": 1, "('yet', 'spoken', 'final')": 1, "('yesterday,', 'involved', 'Islands--continue')": 1, "('yearning', 'people', 'exploited')": 1, "('would', 'intervene', 'way')": 1, "('would', 'expect', 'accept')": 1, "('would', 'contrary', 'traditions')": 1, "('worse', 'instead', 'better')": 1, "('world', 'possess', 'necessary')": 1, "('women', 'fighting', 'redeem')": 1, "('without', 'firing', 'single')": 1, "('without', 'fanfare,', 'thousands')": 1, "('whose', 'character', 'stamped')": 1, "('well', 'must', 'show')": 1, "('well', 'military--peril', 'freedom')": 1, "('ways', 'difficult', 'war,')": 1, "('war,', 'disappointment', 'often')": 1, "('want', 'clearly', 'understood')": 1, "('vulnerable', 'areas', 'one')": 1, "('voices', 'Asia', 'Latin')": 1, "('visionary', 'determine', 'real')": 1, "('villages', 'markets--day', 'night--classrooms')": 1, "('useful', 'lessons', 'us')": 1, "('urgency', 'need', 'combat--whether')": 1, "('upon', \"system's\", 'survival')": 1}}, "Lyndon B. Johnson": {"unigram": {"('space',)": 9, "('great',)": 7, "('us',)": 6, "('honor',)": 6, "('proud',)": 5, "('men',)": 5, "('first',)": 5, "('Space',)": 5, "('today',)": 4, "('man',)": 4, "('young',)": 3, "('years',)": 3, "('two',)": 3, "('team',)": 3, "('room',)": 3, "('role',)": 3, "('purpose',)": 3, "('program',)": 3, "('one',)": 3, "('leadership',)": 3, "('happy',)": 3, "('day',)": 3, "('advance',)": 3, "('Webb',)": 3, "('Senate',)": 3}, "bigram": {"('young', 'Americans,')": 2, "('role', 'space')": 2, "('proud', 'happy')": 2, "('honor', 'Gus')": 2, "('happy', 'occasion')": 2, "('applauding', 'today')": 2, "('Gus', 'Grissom,')": 2, "('Grissom,', 'first')": 2, "('400,000', 'men')": 2, "('young', 'men')": 1, "('years', 'room')": 1, "('years', 'ago,')": 1, "('year', 'passes')": 1, "('would', 'role')": 1, "('would', 'like')": 1, "('women', 'industry,')": 1, "('wives', 'families')": 1, "('witnessed', 'great')": 1, "('wish', 'possible')": 1, "('whether', 'would')": 1, "('wet', 'landing')": 1, "('want', 'thank')": 1, "('vital,', 'useful')": 1, "('vital', 'useful')": 1, "('vital', 'part,')": 1}, "trigram": {"('proud', 'happy', 'occasion')": 2, "('Gus', 'Grissom,', 'first')": 2, "('young', 'men', 'brought')": 1, "('young', 'Americans,', 'including')": 1, "('young', 'Americans,', 'gives')": 1, "('years', 'room', 'witnessed')": 1, "('years', 'ago,', 'many')": 1, "('would', 'role', 'man')": 1, "('would', 'like', 'ask')": 1, "('women', 'industry,', 'campuses,')": 1, "('wives', 'families', 'two')": 1, "('witnessed', 'great', 'moments')": 1, "('wish', 'possible', 'two')": 1, "('whether', 'would', 'role')": 1, "('wet', 'landing', 'Atlantic')": 1, "('want', 'thank', 'coming')": 1, "('vital', 'part,', 'back')": 1, "('vision', 'brought', 'things')": 1, "('valuable', 'public', 'servants,')": 1, "('us,', 'think', 'proud')": 1, "('us', 'mankind', 'dramatic')": 1, "('us', 'far', 'beyond')": 1, "('us', 'conscious', 'crossed')": 1, "('us', 'accomplishments', 'applauding')": 1, "('uniting', 'behind', 'Space')": 1}}, "Warren G. Harding": {"unigram": {"('world',)": 39, "('American',)": 38, "('must',)": 32, "('&',)": 32, "('America',)": 29, "('government',)": 27, "('believe',)": 24, "('Republic',)": 21, "('#39;',)": 18, "('people',)": 16, "('one',)": 16, "('every',)": 16, "('party',)": 15, "('war',)": 14, "('us',)": 14, "('mdash;',)": 14, "('freedom',)": 14, "('call',)": 14, "('shall',)": 12, "('hold',)": 12, "('conscience',)": 12, "('right',)": 11, "('never',)": 11, "('may',)": 11, "('Government',)": 11}, "bigram": {"('&', '#39;')": 18, "('&', 'mdash;')": 14, "('Republican', 'Party')": 5, "('Let', 'us')": 5, "('war', 'emergency')": 3, "('party', 'platform')": 3, "('orderly', 'government')": 3, "('one', 'hand')": 3, "('good', 'fortune')": 3, "('cost', 'living')": 3, "('believe', 'Federal')": 3, "('Federal', 'Government')": 3, "('American', 'people')": 3, "('world', 'ever')": 2, "('world', '&')": 2, "('vision', 'includes')": 2, "('today', 'world')": 2, "('temple', 'liberty')": 2, "('sons', 'Republic')": 2, "('shall', 'asked')": 2, "('sacrifices', 'made')": 2, "('rights', 'freedom')": 2, "('representative', 'democracy')": 2, "('reduced', 'cost')": 2, "('public', 'service')": 2}, "trigram": {"('world', '&', '#39;')": 2, "('reduced', 'cost', 'living')": 2, "('people', '&', '#39;')": 2, "('humanity', '&', '#39;')": 2, "('competition', '&', 'mdash;')": 2, "('believe', 'Federal', 'Government')": 2, "('Government', '&', '#39;')": 2, "('Europe', '&', '#39;')": 2, "('yielded', 'lure', 'shop')": 1, "('yet,', 'somehow,', 'come')": 1, "('years', 'ago,', 'times')": 1, "('yearnings', 'millions', 'American')": 1, "('wrought', 'tragedy', 'pathetic')": 1, "('wrought', 'party', 'government')": 1, "('wrought', 'justice', 'statutes')": 1, "('wrought', 'destruction', 'healthful')": 1, "('written,', 'know', 'whether')": 1, "('written,', 'except', 'work')": 1, "('written', 'compact', 'surrenders')": 1, "('woven', 'history', 'Republic,')": 1, "('wound', 'world', 'war,')": 1, "('would', 'natural', 'self')": 1, "('would', 'look', 'anxiety')": 1, "('would', 'like', 'acclaim')": 1, "('would', 'hopefully', 'approach')": 1}}}